{"total":"7173","results":[{"id":"29442293","race_id":"73970","rank":"1801","name":"Tom Regan","bib":"23742","time":"01:42:43","pace":"04:53","hometown":"\u041c\u043e\u0441\u043a\u0432\u0430, Russia","primary_bracket":"M-\u041c\u0443\u0436\u0447\u0438\u043d\u044bMALE","bracket_id":"786309","interval_id":"149013","checkpoint_id":"216049","checkpoint_name":"Finish","checkpoint_distance":"-21097","event_id":"29755"},{"id":"29443618","race_id":"73970","rank":"1802","name":"Timur Semenov","bib":"27106","time":"01:42:43","pace":"04:53","hometown":"\u041c\u043e\u0441\u043a\u0432\u0430, Russia","primary_bracket":"M-\u041c\u0443\u0436\u0447\u0438\u043d\u044bMALE","bracket_id":"786309","interval_id":"149013","checkpoint_id":"216049","checkpoint_name":"Finish","checkpoint_distance":"-21097","event_id":"29755"},{"id":"29442587","race_id":"73970","rank":"1803","name":"\u0410\u043d\u0442\u043e\u043d \u041a\u0440\u0430\u0448\u0435\u043d\u0438\u043d\u043d\u0438\u043a\u043e\u0432","bib":"26907","time":"01:42:45","pace":"04:53","hometown":"\u041c\u043e\u0441\u043a\u0432\u0430, Russia","primary_bracket":"M-\u041c\u0443\u0436\u0447\u0438\u043d\u044bMALE","bracket_id":"786309","interval_id":"149013","checkpoint_id":"216049","checkpoint_name":"Finish","checkpoint_distance":"-21097","event_id":"29755"},{"id":"29445417","race_id":"73970","rank":"1803","name":"Dmitriy \u0421\u0430\u043c\u0446\u043e\u0432","bib":"25881","time":"01:42:45","pace":"04:53","hometown":"\u041c\u043e\u0441\u043a\u0432\u0430, Russia","primary_bracket":"M-\u041c\u0443\u0436\u0447\u0438\u043d\u044bMALE","bracket_id":"786309","interval_id":"149013","checkpoint_id":"216049","checkpoint_name":"Finish","checkpoint_distance":"-21097","event_id":"29755"},{"id":"29446637","race_id":"73970","rank":"1805","name":"Aleksandr Butov","bib":"24646","time":"01:42:45","pace":"04:53","hometown":"\u041c\u043e\u0441\u043a\u0432\u0430, Russia","primary_bracket":"M-\u041c\u0443\u0436\u0447\u0438\u043d\u044bMALE","bracket_id":"786309","interval_id":"149013","checkpoint_id":"216049","checkpoint_name":"Finish","checkpoint_distance":"-21097","event_id":"29755"},{"id":"29443404","race_id":"73970","rank":"1806","name":"\u041c\u0430\u043a\u0441\u0438\u043c \u0412\u0430\u0441\u0438\u043b\u044c\u0435\u0432","bib":"21074","time":"01:42:45","pace":"04:53","hometown":"\u041c\u043e\u0441\u043a\u0432\u0430, Russia","primary_bracket":"M-\u041c\u0443\u0436\u0447\u0438\u043d\u044bMALE","bracket_id":"786309","interval_id":"149013","checkpoint_id":"216049","checkpoint_name":"Finish","checkpoint_distance":"-21097","event_id":"29755"},{"id":"29444657","race_id":"73970","rank":"1807","name":"\u0418\u043b\u044c\u044f \u0412\u0430\u043a\u043e\u043b\u044e\u043a","bib":"27307","time":"01:42:45","pace":"04:53","hometown":"\u041c\u043e\u0441\u043a\u0432\u0430, Russia","primary_bracket":"M-\u041c\u0443\u0436\u0447\u0438\u043d\u044bMALE","bracket_id":"786309","interval_id":"149013","checkpoint_id":"216049","checkpoint_name":"Finish","checkpoint_distance":"-21097","event_id":"29755"},{"id":"29444956","race_id":"73970","rank":"1808","name":"\u041c\u0430\u043a\u0441\u0438\u043c \u041e\u0440\u043b\u043e\u0432","bib":"24245","time":"01:42:45","pace":"04:53","hometown":"\u041c\u043e\u0441\u043a\u0432\u0430, Russia","primary_bracket":"M-\u041c\u0443\u0436\u0447\u0438\u043d\u044bMALE","bracket_id":"786309","interval_id":"149013","checkpoint_id":"216049","checkpoint_name":"Finish","checkpoint_distance":"-21097","event_id":"29755"},{"id":"29591453","race_id":"73970","rank":"1809","name":"Dmitry Nazarov","bib":"28378","time":"01:42:45","pace":"04:53","hometown":"\u041c\u043e\u0441\u043a\u0432\u0430, Russia","primary_bracket":"M-\u041c\u0443\u0436\u0447\u0438\u043d\u044bMALE","bracket_id":"786309","interval_id":"149013","checkpoint_id":"216049","checkpoint_name":"Finish","checkpoint_distance":"-21097","event_id":"29755"},{"id":"29443620","race_id":"73970","rank":"1810","name":"\u0412\u043b\u0430\u0434\u0438\u043c\u0438\u0440 \u041f\u043e\u043b\u0438\u043a\u0443\u0448\u0438\u043d","bib":"25543","time":"01:42:46","pace":"04:53","hometown":"\u041d\u041e\u0413\u0418\u041d\u0421\u041a, Russia","primary_bracket":"M-\u041c\u0443\u0436\u0447\u0438\u043d\u044bMALE","bracket_id":"786309","interval_id":"149013","checkpoint_id":"216049","checkpoint_name":"Finish","checkpoint_distance":"-21097","event_id":"29755"},{"id":"29440922","race_id":"73970","rank":"1811","name":"\u0414\u0435\u043d\u0438\u0441 \u0424\u0430\u0442\u0435\u0440\u043a\u0438\u043d","bib":"23481","time":"01:42:46","pace":"04:53","hometown":"\u041c\u043e\u0441\u043a\u0432\u0430, Russia","primary_bracket":"M-\u041c\u0443\u0436\u0447\u0438\u043d\u044bMALE","bracket_id":"786309","interval_id":"149013","checkpoint_id":"216049","checkpoint_name":"Finish","checkpoint_distance":"-21097","event_id":"29755"},{"id":"29442272","race_id":"73970","rank":"1812","name":"\u0418\u0433\u043e\u0440\u044c \u0417\u0430\u0439\u0446\u0435\u0432","bib":"20802","time":"01:42:47","pace":"04:53","hometown":"\u041c\u043e\u0441\u043a\u0432\u0430, Russia","primary_bracket":"M-\u041c\u0443\u0436\u0447\u0438\u043d\u044bMALE","bracket_id":"786309","interval_id":"149013","checkpoint_id":"216049","checkpoint_name":"Finish","checkpoint_distance":"-21097","event_id":"29755"},{"id":"29444791","race_id":"73970","rank":"1813","name":"\u0410\u043b\u0435\u043a\u0441\u0430\u043d\u0434\u0440 \u041a\u043e\u043d\u043e\u0432\u0430\u043b\u043e\u0432","bib":"22663","time":"01:42:47","pace":"04:53","hometown":"\u0411\u0430\u043b\u0430\u0448\u0438\u0445\u0430, Russia","primary_bracket":"M-\u041c\u0443\u0436\u0447\u0438\u043d\u044bMALE","bracket_id":"786309","interval_id":"149013","checkpoint_id":"216049","checkpoint_name":"Finish","checkpoint_distance":"-21097","event_id":"29755"},{"id":"29443933","race_id":"73970","rank":"1814","name":"Borut Nastran","bib":"24052","time":"01:42:48","pace":"04:53","hometown":"\u041c\u043e\u0441\u043a\u0432\u0430, Russia","primary_bracket":"M-\u041c\u0443\u0436\u0447\u0438\u043d\u044bMALE","bracket_id":"786309","interval_id":"149013","checkpoint_id":"216049","checkpoint_name":"Finish","checkpoint_distance":"-21097","event_id":"29755"},{"id":"29441936","race_id":"73970","rank":"1815","name":"\u0418\u0432\u0430\u043d \u0416\u0443\u043a","bib":"23674","time":"01:42:48","pace":"04:53","hometown":"\u0412\u0418\u0414\u041d\u041e\u0415, Russia","primary_bracket":"M-\u041c\u0443\u0436\u0447\u0438\u043d\u044bMALE","bracket_id":"786309","interval_id":"149013","checkpoint_id":"216049","checkpoint_name":"Finish","checkpoint_distance":"-21097","event_id":"29755"},{"id":"29442117","race_id":"73970","rank":"1816","name":"\u041c\u0430\u0440\u0438\u043d\u0430 \u041a\u0443\u0437\u043d\u0435\u0446\u043e\u0432\u0430","bib":"26816","time":"01:42:48","pace":"04:53","hometown":"\u041c\u043e\u0441\u043a\u0432\u0430, Russia","primary_bracket":"F-\u0416\u0435\u043d\u0449\u0438\u043d\u044bFEMALE","bracket_id":"786309","interval_id":"149013","checkpoint_id":"216049","checkpoint_name":"Finish","checkpoint_distance":"-21097","event_id":"29755"},{"id":"29442882","race_id":"73970","rank":"1817","name":"Oleg Golubev","bib":"23853","time":"01:42:48","pace":"04:53","hometown":"\u041c\u043e\u0441\u043a\u0432\u0430, Russia","primary_bracket":"M-\u041c\u0443\u0436\u0447\u0438\u043d\u044bMALE","bracket_id":"786309","interval_id":"149013","checkpoint_id":"216049","checkpoint_name":"Finish","checkpoint_distance":"-21097","event_id":"29755"},{"id":"29439144","race_id":"73970","rank":"1818","name":"\u0410\u043b\u0435\u043a\u0441\u0435\u0439 \u041c\u0443\u0437\u044b\u043a\u0438\u043d","bib":"26241","time":"01:42:48","pace":"04:53","hometown":"\u041c\u043e\u0441\u043a\u0432\u0430, Russia","primary_bracket":"M-\u041c\u0443\u0436\u0447\u0438\u043d\u044bMALE","bracket_id":"786309","interval_id":"149013","checkpoint_id":"216049","checkpoint_name":"Finish","checkpoint_distance":"-21097","event_id":"29755"},{"id":"29442077","race_id":"73970","rank":"1819","name":"\u0410\u0440\u0442\u0443\u0440 \u041f\u0430\u0440\u0441\u043a\u043e\u0432","bib":"23701","time":"01:42:49","pace":"04:53","hometown":"\u041c\u043e\u0441\u043a\u0432\u0430, Russia","primary_bracket":"M-\u041c\u0443\u0436\u0447\u0438\u043d\u044bMALE","bracket_id":"786309","interval_id":"149013","checkpoint_id":"216049","checkpoint_name":"Finish","checkpoint_distance":"-21097","event_id":"29755"},{"id":"29443792","race_id":"73970","rank":"1820","name":"Thomas Hodgkinson","bib":"22474","time":"01:42:51","pace":"04:53","hometown":"\u041c\u043e\u0441\u043a\u0432\u0430, Russia","primary_bracket":"M-\u041c\u0443\u0436\u0447\u0438\u043d\u044bMALE","bracket_id":"786309","interval_id":"149013","checkpoint_id":"216049","checkpoint_name":"Finish","checkpoint_distance":"-21097","event_id":"29755"},{"id":"29442680","race_id":"73970","rank":"1821","name":"\u0410\u043b\u0435\u043a\u0441\u0430\u043d\u0434\u0440 \u0418\u0432\u0430\u043d\u043e\u0432","bib":"25364","time":"01:42:51","pace":"04:53","hometown":"\u041c\u043e\u0441\u043a\u0432\u0430, Russia","primary_bracket":"M-\u041c\u0443\u0436\u0447\u0438\u043d\u044bMALE","bracket_id":"786309","interval_id":"149013","checkpoint_id":"216049","checkpoint_name":"Finish","checkpoint_distance":"-21097","event_id":"29755"},{"id":"29442769","race_id":"73970","rank":"1822","name":"\u042f\u0440\u043e\u0441\u043b\u0430\u0432 \u0412\u043e\u0440\u043e\u0431\u044c\u0435\u0432","bib":"25381","time":"01:42:51","pace":"04:53","hometown":"\u041c\u043e\u0441\u043a\u0432\u0430, Russia","primary_bracket":"M-\u041c\u0443\u0436\u0447\u0438\u043d\u044bMALE","bracket_id":"786309","interval_id":"149013","checkpoint_id":"216049","checkpoint_name":"Finish","checkpoint_distance":"-21097","event_id":"29755"},{"id":"29445689","race_id":"73970","rank":"1823","name":"\u041a\u043e\u043d\u0441\u0442\u0430\u043d\u0442\u0438\u043d \u041c\u0438\u043b\u043e\u0432\u0438\u0434\u043e\u0432","bib":"24403","time":"01:42:51","pace":"04:53","hometown":"\u041c\u043e\u0441\u043a\u0432\u0430, Russia","primary_bracket":"M-\u041c\u0443\u0436\u0447\u0438\u043d\u044bMALE","bracket_id":"786309","interval_id":"149013","checkpoint_id":"216049","checkpoint_name":"Finish","checkpoint_distance":"-21097","event_id":"29755"},{"id":"29446058","race_id":"73970","rank":"1824","name":"Pierre Antunes","bib":"22943","time":"01:42:52","pace":"04:53","hometown":"\u041c\u043e\u0441\u043a\u0432\u0430, Russia","primary_bracket":"M-\u041c\u0443\u0436\u0447\u0438\u043d\u044bMALE","bracket_id":"786309","interval_id":"149013","checkpoint_id":"216049","checkpoint_name":"Finish","checkpoint_distance":"-21097","event_id":"29755"},{"id":"29441929","race_id":"73970","rank":"1825","name":"\u0413\u0430\u0440\u044f \u0414\u043e\u043d\u0438\u0441\u043e\u0432","bib":"22123","time":"01:42:52","pace":"04:53","hometown":"\u042d\u043b\u0438\u0441\u0442\u0430, Russia","primary_bracket":"M-\u041c\u0443\u0436\u0447\u0438\u043d\u044bMALE","bracket_id":"786309","interval_id":"149013","checkpoint_id":"216049","checkpoint_name":"Finish","checkpoint_distance":"-21097","event_id":"29755"},{"id":"29442109","race_id":"73970","rank":"1826","name":"Darya Ierusalimskaya","bib":"20763","time":"01:42:52","pace":"04:53","hometown":"\u041c\u043e\u0441\u043a\u0432\u0430, Russia","primary_bracket":"F-\u0416\u0435\u043d\u0449\u0438\u043d\u044bFEMALE","bracket_id":"786309","interval_id":"149013","checkpoint_id":"216049","checkpoint_name":"Finish","checkpoint_distance":"-21097","event_id":"29755"},{"id":"29442440","race_id":"73970","rank":"1827","name":"\u0415\u0432\u0433\u0435\u043d\u0438\u0439 \u0412\u043e\u0440\u043e\u043d\u043e\u0432","bib":"20843","time":"01:42:52","pace":"04:53","hometown":"\u041c\u041e\u041d\u0418\u041d\u041e, Russia","primary_bracket":"M-\u041c\u0443\u0436\u0447\u0438\u043d\u044bMALE","bracket_id":"786309","interval_id":"149013","checkpoint_id":"216049","checkpoint_name":"Finish","checkpoint_distance":"-21097","event_id":"29755"},{"id":"29571021","race_id":"73970","rank":"1828","name":"\u042e\u0440\u0438\u0439 \u041a\u0430\u0448\u0442\u0430\u043d\u043e\u0432","bib":"27795","time":"01:42:52","pace":"04:53","hometown":"\u041c\u043e\u0441\u043a\u0432\u0430, Russia","primary_bracket":"M-\u041c\u0443\u0436\u0447\u0438\u043d\u044bMALE","bracket_id":"786309","interval_id":"149013","checkpoint_id":"216049","checkpoint_name":"Finish","checkpoint_distance":"-21097","event_id":"29755"},{"id":"29445859","race_id":"73970","rank":"1829","name":"\u0414\u0435\u043d\u0438\u0441 \u0421\u0443\u0442\u0435\u0440","bib":"22894","time":"01:42:52","pace":"04:53","hometown":"\u041c\u043e\u0441\u043a\u0432\u0430, Russia","primary_bracket":"M-\u041c\u0443\u0436\u0447\u0438\u043d\u044bMALE","bracket_id":"786309","interval_id":"149013","checkpoint_id":"216049","checkpoint_name":"Finish","checkpoint_distance":"-21097","event_id":"29755"},{"id":"29444056","race_id":"73970","rank":"1830","name":"\u0410\u043d\u0434\u0440\u0435\u0439 \u041b\u0430\u0440\u0438\u043e\u043d\u043e\u0432","bib":"21230","time":"01:42:53","pace":"04:53","hometown":"\u041c\u043e\u0441\u043a\u0432\u0430, Russia","primary_bracket":"M-\u041c\u0443\u0436\u0447\u0438\u043d\u044bMALE","bracket_id":"786309","interval_id":"149013","checkpoint_id":"216049","checkpoint_name":"Finish","checkpoint_distance":"-21097","event_id":"29755"},{"id":"29439764","race_id":"73970","rank":"1831","name":"\u0418\u0432\u0430\u043d \u0428\u0438\u044f\u043d\u043e\u0432","bib":"23260","time":"01:42:53","pace":"04:53","hometown":"\u041c\u043e\u0441\u043a\u0432\u0430, Russia","primary_bracket":"M-\u041c\u0443\u0436\u0447\u0438\u043d\u044bMALE","bracket_id":"786309","interval_id":"149013","checkpoint_id":"216049","checkpoint_name":"Finish","checkpoint_distance":"-21097","event_id":"29755"},{"id":"29441025","race_id":"73970","rank":"1832","name":"\u0410\u043b\u0435\u043a\u0441\u0435\u0439 \u0414\u0440\u043e\u0437\u0434\u043e\u0432","bib":"20506","time":"01:42:53","pace":"04:53","hometown":"\u041c\u043e\u0441\u043a\u0432\u0430, Russia","primary_bracket":"M-\u041c\u0443\u0436\u0447\u0438\u043d\u044bMALE","bracket_id":"786309","interval_id":"149013","checkpoint_id":"216049","checkpoint_name":"Finish","checkpoint_distance":"-21097","event_id":"29755"},{"id":"29445648","race_id":"73970","rank":"1833","name":"\u0421\u0435\u0440\u0433\u0435\u0439 \u041e\u0442\u0432\u043e\u0434\u0435\u043d\u043a\u043e\u0432","bib":"22842","time":"01:42:54","pace":"04:53","hometown":"\u041c\u043e\u0441\u043a\u0432\u0430, Russia","primary_bracket":"M-\u041c\u0443\u0436\u0447\u0438\u043d\u044bMALE","bracket_id":"786309","interval_id":"149013","checkpoint_id":"216049","checkpoint_name":"Finish","checkpoint_distance":"-21097","event_id":"29755"},{"id":"29445842","race_id":"73970","rank":"1834","name":"\u0421\u0435\u0440\u0433\u0435\u0439 \u041f\u0430\u0440\u0430\u043c\u043e\u043d\u043e\u0432","bib":"25987","time":"01:42:54","pace":"04:53","hometown":"\u041c\u043e\u0441\u043a\u0432\u0430, Russia","primary_bracket":"M-\u041c\u0443\u0436\u0447\u0438\u043d\u044bMALE","bracket_id":"786309","interval_id":"149013","checkpoint_id":"216049","checkpoint_name":"Finish","checkpoint_distance":"-21097","event_id":"29755"},{"id":"29444630","race_id":"73970","rank":"1835","name":"\u0420\u0430\u043c\u0438\u043b\u044c \u042e\u0441\u0443\u043f\u043e\u0432","bib":"27302","time":"01:42:54","pace":"04:53","hometown":"\u041c\u043e\u0441\u043a\u0432\u0430, Russia","primary_bracket":"M-\u041c\u0443\u0436\u0447\u0438\u043d\u044bMALE","bracket_id":"786309","interval_id":"149013","checkpoint_id":"216049","checkpoint_name":"Finish","checkpoint_distance":"-21097","event_id":"29755"},{"id":"29439951","race_id":"73970","rank":"1836","name":"Alexandr Yakovlev","bib":"21747","time":"01:42:55","pace":"04:53","hometown":"\u041c\u043e\u0441\u043a\u0432\u0430, Russia","primary_bracket":"M-\u041c\u0443\u0436\u0447\u0438\u043d\u044bMALE","bracket_id":"786309","interval_id":"149013","checkpoint_id":"216049","checkpoint_name":"Finish","checkpoint_distance":"-21097","event_id":"29755"},{"id":"29440291","race_id":"73970","rank":"1837","name":"Evgeny Papshev","bib":"24913","time":"01:42:55","pace":"04:53","hometown":"\u041c\u043e\u0441\u043a\u0432\u0430, Russia","primary_bracket":"M-\u041c\u0443\u0436\u0447\u0438\u043d\u044bMALE","bracket_id":"786309","interval_id":"149013","checkpoint_id":"216049","checkpoint_name":"Finish","checkpoint_distance":"-21097","event_id":"29755"},{"id":"29442290","race_id":"73970","rank":"1838","name":"Denis Kleptsyn","bib":"25291","time":"01:42:55","pace":"04:53","hometown":"\u041c\u043e\u0441\u043a\u0432\u0430, Russia","primary_bracket":"M-\u041c\u0443\u0436\u0447\u0438\u043d\u044bMALE","bracket_id":"786309","interval_id":"149013","checkpoint_id":"216049","checkpoint_name":"Finish","checkpoint_distance":"-21097","event_id":"29755"},{"id":"29445794","race_id":"73970","rank":"1839","name":"Neil Boyd","bib":"22878","time":"01:42:56","pace":"04:53","hometown":"\u041c\u043e\u0441\u043a\u0432\u0430, Russia","primary_bracket":"M-\u041c\u0443\u0436\u0447\u0438\u043d\u044bMALE","bracket_id":"786309","interval_id":"149013","checkpoint_id":"216049","checkpoint_name":"Finish","checkpoint_distance":"-21097","event_id":"29755"},{"id":"29442738","race_id":"73970","rank":"1840","name":"\u0410\u043b\u0435\u043a\u0441\u0430\u043d\u0434\u0440 \u0414\u0443\u0448\u0435\u043d\u043e\u043a","bib":"25375","time":"01:42:56","pace":"04:53","hometown":"\u041c\u043e\u0441\u043a\u0432\u0430, Russia","primary_bracket":"M-\u041c\u0443\u0436\u0447\u0438\u043d\u044bMALE","bracket_id":"786309","interval_id":"149013","checkpoint_id":"216049","checkpoint_name":"Finish","checkpoint_distance":"-21097","event_id":"29755"},{"id":"29444632","race_id":"73970","rank":"1841","name":"Maxim Kolesnikov","bib":"25735","time":"01:42:57","pace":"04:53","hometown":"\u041c\u043e\u0441\u043a\u0432\u0430, Russia","primary_bracket":"M-\u041c\u0443\u0436\u0447\u0438\u043d\u044bMALE","bracket_id":"786309","interval_id":"149013","checkpoint_id":"216049","checkpoint_name":"Finish","checkpoint_distance":"-21097","event_id":"29755"},{"id":"29443548","race_id":"73970","rank":"1842","name":"Denis Popov","bib":"25529","time":"01:42:57","pace":"04:53","hometown":"\u041c\u043e\u0441\u043a\u0432\u0430, Russia","primary_bracket":"M-\u041c\u0443\u0436\u0447\u0438\u043d\u044bMALE","bracket_id":"786309","interval_id":"149013","checkpoint_id":"216049","checkpoint_name":"Finish","checkpoint_distance":"-21097","event_id":"29755"},{"id":"29445802","race_id":"73970","rank":"1843","name":"Marissa Lane","bib":"22880","time":"01:42:57","pace":"04:53","hometown":"\u041c\u043e\u0441\u043a\u0432\u0430, Russia","primary_bracket":"F-\u0416\u0435\u043d\u0449\u0438\u043d\u044bFEMALE","bracket_id":"786309","interval_id":"149013","checkpoint_id":"216049","checkpoint_name":"Finish","checkpoint_distance":"-21097","event_id":"29755"},{"id":"29439453","race_id":"73970","rank":"1844","name":"\u0421\u0435\u0440\u0433\u0435\u0439 \u0421\u044b\u0447\u0443\u0433\u043e\u0432","bib":"26301","time":"01:42:57","pace":"04:53","hometown":"\u041c\u043e\u0441\u043a\u0432\u0430, Russia","primary_bracket":"M-\u041c\u0443\u0436\u0447\u0438\u043d\u044bMALE","bracket_id":"786309","interval_id":"149013","checkpoint_id":"216049","checkpoint_name":"Finish","checkpoint_distance":"-21097","event_id":"29755"},{"id":"29439996","race_id":"73970","rank":"1845","name":"\u0415\u0432\u0433\u0435\u043d\u0438\u0439 \u0414\u0443\u0448\u0435\u043d\u043e\u043a","bib":"26406","time":"01:42:59","pace":"04:53","hometown":"\u041c\u043e\u0441\u043a\u0432\u0430, Russia","primary_bracket":"M-\u041c\u0443\u0436\u0447\u0438\u043d\u044bMALE","bracket_id":"786309","interval_id":"149013","checkpoint_id":"216049","checkpoint_name":"Finish","checkpoint_distance":"-21097","event_id":"29755"},{"id":"29446586","race_id":"73970","rank":"1846","name":"\u041c\u0438\u0445\u0430\u0438\u043b \u0422\u0440\u043e\u0444\u0438\u043c\u043e\u0432","bib":"24629","time":"01:42:59","pace":"04:53","hometown":"\u041c\u043e\u0441\u043a\u0432\u0430, Russia","primary_bracket":"M-\u041c\u0443\u0436\u0447\u0438\u043d\u044bMALE","bracket_id":"786309","interval_id":"149013","checkpoint_id":"216049","checkpoint_name":"Finish","checkpoint_distance":"-21097","event_id":"29755"},{"id":"29441247","race_id":"73970","rank":"1847","name":"\u0412\u043b\u0430\u0434\u0438\u043c\u0438\u0440 \u041f\u0435\u0442\u0440\u0443\u0448\u043a\u0438\u043d","bib":"20559","time":"01:43:00","pace":"04:53","hometown":"\u041c\u043e\u0441\u043a\u0432\u0430, Russia","primary_bracket":"M-\u041c\u0443\u0436\u0447\u0438\u043d\u044bMALE","bracket_id":"786309","interval_id":"149013","checkpoint_id":"216049","checkpoint_name":"Finish","checkpoint_distance":"-21097","event_id":"29755"},{"id":"29444099","race_id":"73970","rank":"1848","name":"\u0420\u043e\u043c\u0430\u043d \u041a\u0440\u044e\u0447\u043a\u043e\u0432","bib":"27199","time":"01:43:00","pace":"04:53","hometown":"\u041c\u043e\u0441\u043a\u0432\u0430, Russia","primary_bracket":"M-\u041c\u0443\u0436\u0447\u0438\u043d\u044bMALE","bracket_id":"786309","interval_id":"149013","checkpoint_id":"216049","checkpoint_name":"Finish","checkpoint_distance":"-21097","event_id":"29755"},{"id":"29441635","race_id":"73970","rank":"1849","name":"\u041d\u0438\u043a\u0438\u0442\u0430 \u0422\u0438\u0442\u043e\u0432","bib":"26723","time":"01:43:00","pace":"04:53","hometown":"\u0412\u043e\u0440\u043e\u043d\u0435\u0436, Russia","primary_bracket":"M-\u041c\u0443\u0436\u0447\u0438\u043d\u044bMALE","bracket_id":"786309","interval_id":"149013","checkpoint_id":"216049","checkpoint_name":"Finish","checkpoint_distance":"-21097","event_id":"29755"},{"id":"29441795","race_id":"73970","rank":"1850","name":"\u0410\u043b\u0435\u043a\u0441\u0430\u043d\u0434\u0440 \u041f\u0438\u0441\u043a\u0443\u043d\u043e\u0432","bib":"22097","time":"01:43:01","pace":"04:53","hometown":"\u041c\u043e\u0441\u043a\u0432\u0430, Russia","primary_bracket":"M-\u041c\u0443\u0436\u0447\u0438\u043d\u044bMALE","bracket_id":"786309","interval_id":"149013","checkpoint_id":"216049","checkpoint_name":"Finish","checkpoint_distance":"-21097","event_id":"29755"},{"id":"29445188","race_id":"73970","rank":"1851","name":"Valeriy Belokurov","bib":"22740","time":"01:43:02","pace":"04:53","hometown":"\u041c\u043e\u0441\u043a\u0432\u0430, Russia","primary_bracket":"M-\u041c\u0443\u0436\u0447\u0438\u043d\u044bMALE","bracket_id":"786309","interval_id":"149013","checkpoint_id":"216049","checkpoint_name":"Finish","checkpoint_distance":"-21097","event_id":"29755"},{"id":"29439170","race_id":"73970","rank":"1852","name":"\u041c\u0438\u043d\u044c\u043a\u0430 \u0427\u0430\u0439\u043a\u0438\u043d","bib":"26246","time":"01:43:03","pace":"04:54","hometown":"\u041c\u043e\u0441\u043a\u0432\u0430, Russia","primary_bracket":"M-\u041c\u0443\u0436\u0447\u0438\u043d\u044bMALE","bracket_id":"786309","interval_id":"149013","checkpoint_id":"216049","checkpoint_name":"Finish","checkpoint_distance":"-21097","event_id":"29755"},{"id":"29444837","race_id":"73970","rank":"1853","name":"\u0410\u043b\u0435\u043a\u0441\u0435\u0439 \u041a\u043d\u044f\u0436\u0438\u043d","bib":"25774","time":"01:43:03","pace":"04:54","hometown":"\u041a\u0420\u0410\u0421\u041d\u041e\u0413\u041e\u0420\u0421\u041a, Russia","primary_bracket":"M-\u041c\u0443\u0436\u0447\u0438\u043d\u044bMALE","bracket_id":"786309","interval_id":"149013","checkpoint_id":"216049","checkpoint_name":"Finish","checkpoint_distance":"-21097","event_id":"29755"},{"id":"29570991","race_id":"73970","rank":"1854","name":"\u041a\u0438\u0440\u0438\u043b\u043b \u041d\u0435\u0441\u0442\u0435\u0440\u043e\u0432","bib":"28052","time":"01:43:03","pace":"04:54","hometown":"\u041c\u043e\u0441\u043a\u0432\u0430, Russia","primary_bracket":"M-\u041c\u0443\u0436\u0447\u0438\u043d\u044bMALE","bracket_id":"786309","interval_id":"149013","checkpoint_id":"216049","checkpoint_name":"Finish","checkpoint_distance":"-21097","event_id":"29755"},{"id":"29441590","race_id":"73970","rank":"1854","name":"\u0414\u043c\u0438\u0442\u0440\u0438\u0439 \u041f\u043e\u0439\u043a\u0430\u043b\u0430\u0439\u043d\u0435\u043d","bib":"20640","time":"01:43:03","pace":"04:54","hometown":"\u041c\u043e\u0441\u043a\u0432\u0430, Russia","primary_bracket":"M-\u041c\u0443\u0436\u0447\u0438\u043d\u044bMALE","bracket_id":"786309","interval_id":"149013","checkpoint_id":"216049","checkpoint_name":"Finish","checkpoint_distance":"-21097","event_id":"29755"},{"id":"29442575","race_id":"73970","rank":"1856","name":"\u041c\u0430\u043a\u0441\u0438\u043c \u0418\u0432\u0430\u043d\u043e\u0432","bib":"20875","time":"01:43:04","pace":"04:54","hometown":"\u041c\u043e\u0441\u043a\u0432\u0430, Russia","primary_bracket":"M-\u041c\u0443\u0436\u0447\u0438\u043d\u044bMALE","bracket_id":"786309","interval_id":"149013","checkpoint_id":"216049","checkpoint_name":"Finish","checkpoint_distance":"-21097","event_id":"29755"},{"id":"29446374","race_id":"73970","rank":"1857","name":"\u0420\u0430\u0444\u0430\u0438\u043b\u044c \u0410\u0445\u043c\u0430\u0434\u0443\u043b\u043b\u0438\u043d","bib":"26119","time":"01:43:04","pace":"04:54","hometown":"\u041c\u043e\u0441\u043a\u0432\u0430, Russia","primary_bracket":"M-\u041c\u0443\u0436\u0447\u0438\u043d\u044bMALE","bracket_id":"786309","interval_id":"149013","checkpoint_id":"216049","checkpoint_name":"Finish","checkpoint_distance":"-21097","event_id":"29755"},{"id":"29443222","race_id":"73970","rank":"1858","name":"\u0410\u043b\u0435\u043a\u0441\u0430\u043d\u0434\u0440 \u0415\u043b\u0430\u043a\u043e\u0432","bib":"25467","time":"01:43:05","pace":"04:54","hometown":"\u041c\u043e\u0441\u043a\u0432\u0430, Russia","primary_bracket":"M-\u041c\u0443\u0436\u0447\u0438\u043d\u044bMALE","bracket_id":"786309","interval_id":"149013","checkpoint_id":"216049","checkpoint_name":"Finish","checkpoint_distance":"-21097","event_id":"29755"},{"id":"29440384","race_id":"73970","rank":"1859","name":"\u0410\u043b\u0435\u043a\u0441\u0430\u043d\u0434\u0440 \u0412\u043e\u0439\u0442\u043e\u0432\u0438\u0447","bib":"24931","time":"01:43:06","pace":"04:54","hometown":"\u041c\u043e\u0441\u043a\u0432\u0430, Russia","primary_bracket":"M-\u041c\u0443\u0436\u0447\u0438\u043d\u044bMALE","bracket_id":"786309","interval_id":"149013","checkpoint_id":"216049","checkpoint_name":"Finish","checkpoint_distance":"-21097","event_id":"29755"},{"id":"29439016","race_id":"73970","rank":"1860","name":"\u0414\u043c\u0438\u0442\u0440\u0438\u0439 \u0421\u043a\u0443\u0440\u0438\u0434\u0438\u043d","bib":"26216","time":"01:43:06","pace":"04:54","hometown":"\u041c\u043e\u0441\u043a\u0432\u0430, Russia","primary_bracket":"M-\u041c\u0443\u0436\u0447\u0438\u043d\u044bMALE","bracket_id":"786309","interval_id":"149013","checkpoint_id":"216049","checkpoint_name":"Finish","checkpoint_distance":"-21097","event_id":"29755"},{"id":"29446140","race_id":"73970","rank":"1861","name":"\u0410\u043d\u0442\u043e\u043d \u0422\u0435\u0440\u043b\u0435\u0446\u043a\u0438\u0439","bib":"24516","time":"01:43:06","pace":"04:54","hometown":"\u041c\u043e\u0441\u043a\u0432\u0430, Russia","primary_bracket":"M-\u041c\u0443\u0436\u0447\u0438\u043d\u044bMALE","bracket_id":"786309","interval_id":"149013","checkpoint_id":"216049","checkpoint_name":"Finish","checkpoint_distance":"-21097","event_id":"29755"},{"id":"29440026","race_id":"73970","rank":"1862","name":"\u041d\u0438\u043a\u043e\u043b\u0430\u0439 \u0428\u043b\u0430\u043f\u0430\u043a\u043e\u0432","bib":"23310","time":"01:43:07","pace":"04:54","hometown":"\u041c\u043e\u0441\u043a\u0432\u0430, Russia","primary_bracket":"M-\u041c\u0443\u0436\u0447\u0438\u043d\u044bMALE","bracket_id":"786309","interval_id":"149013","checkpoint_id":"216049","checkpoint_name":"Finish","checkpoint_distance":"-21097","event_id":"29755"},{"id":"29446579","race_id":"73970","rank":"1863","name":"\u0410\u043b\u0435\u043a\u0441\u0430\u043d\u0434\u0440 \u041c\u0430\u043c\u0430\u0435\u0432","bib":"26170","time":"01:43:07","pace":"04:54","hometown":"\u041c\u043e\u0441\u043a\u0432\u0430, Russia","primary_bracket":"M-\u041c\u0443\u0436\u0447\u0438\u043d\u044bMALE","bracket_id":"786309","interval_id":"149013","checkpoint_id":"216049","checkpoint_name":"Finish","checkpoint_distance":"-21097","event_id":"29755"},{"id":"29591665","race_id":"73970","rank":"1864","name":"\u0410\u043d\u0442\u043e\u043d \u0414\u0443\u0431\u0440\u043e\u0432\u0438\u043d","bib":"28309","time":"01:43:07","pace":"04:54","hometown":"\u041c\u043e\u0441\u043a\u0432\u0430, Russia","primary_bracket":"M-\u041c\u0443\u0436\u0447\u0438\u043d\u044bMALE","bracket_id":"786309","interval_id":"149013","checkpoint_id":"216049","checkpoint_name":"Finish","checkpoint_distance":"-21097","event_id":"29755"},{"id":"29445548","race_id":"73970","rank":"1865","name":"\u0410\u043b\u0435\u043a\u0441\u0430\u043d\u0434\u0440 \u0420\u0435\u043f\u0438\u043d","bib":"24368","time":"01:43:08","pace":"04:54","hometown":"\u041c\u043e\u0441\u043a\u0432\u0430, Russia","primary_bracket":"M-\u041c\u0443\u0436\u0447\u0438\u043d\u044bMALE","bracket_id":"786309","interval_id":"149013","checkpoint_id":"216049","checkpoint_name":"Finish","checkpoint_distance":"-21097","event_id":"29755"},{"id":"29441930","race_id":"73970","rank":"1866","name":"\u041e\u043b\u0435\u0433 \u0421\u0430\u043d\u0430\u0435\u0432","bib":"23673","time":"01:43:08","pace":"04:54","hometown":"\u041c\u043e\u0441\u043a\u0432\u0430, Russia","primary_bracket":"M-\u041c\u0443\u0436\u0447\u0438\u043d\u044bMALE","bracket_id":"786309","interval_id":"149013","checkpoint_id":"216049","checkpoint_name":"Finish","checkpoint_distance":"-21097","event_id":"29755"},{"id":"29442216","race_id":"73970","rank":"1867","name":"\u0414\u043c\u0438\u0442\u0440\u0438\u0439 \u041a\u043e\u0445\u043e\u0432","bib":"26835","time":"01:43:08","pace":"04:54","hometown":"\u041c\u043e\u0441\u043a\u0432\u0430, Russia","primary_bracket":"M-\u041c\u0443\u0436\u0447\u0438\u043d\u044bMALE","bracket_id":"786309","interval_id":"149013","checkpoint_id":"216049","checkpoint_name":"Finish","checkpoint_distance":"-21097","event_id":"29755"},{"id":"29441047","race_id":"73970","rank":"1868","name":"\u0414\u043c\u0438\u0442\u0440\u0438\u0439 \u041f\u0430\u0432\u043b\u043e\u0432","bib":"26608","time":"01:43:08","pace":"04:54","hometown":"\u041c\u043e\u0441\u043a\u0432\u0430, Russia","primary_bracket":"M-\u041c\u0443\u0436\u0447\u0438\u043d\u044bMALE","bracket_id":"786309","interval_id":"149013","checkpoint_id":"216049","checkpoint_name":"Finish","checkpoint_distance":"-21097","event_id":"29755"},{"id":"29441090","race_id":"73970","rank":"1869","name":"\u041d\u0430\u0434\u0435\u0436\u0434\u0430 \u0423\u0448\u0430\u043a\u043e\u0432\u0430","bib":"25066","time":"01:43:08","pace":"04:54","hometown":"\u041c\u0426\u0415\u041d\u0421\u041a, Russia","primary_bracket":"F-\u0416\u0435\u043d\u0449\u0438\u043d\u044bFEMALE","bracket_id":"786309","interval_id":"149013","checkpoint_id":"216049","checkpoint_name":"Finish","checkpoint_distance":"-21097","event_id":"29755"},{"id":"29445666","race_id":"73970","rank":"1870","name":"\u0415\u0432\u0433\u0435\u043d\u0438\u0439 \u0413\u0438\u043b\u0435\u0442\u0430","bib":"27519","time":"01:43:09","pace":"04:54","hometown":"\u041d\u043e\u0432\u043e\u0441\u0438\u0431\u0438\u0440\u0441\u043a, Russia","primary_bracket":"M-\u041c\u0443\u0436\u0447\u0438\u043d\u044bMALE","bracket_id":"786309","interval_id":"149013","checkpoint_id":"216049","checkpoint_name":"Finish","checkpoint_distance":"-21097","event_id":"29755"},{"id":"29443720","race_id":"73970","rank":"1871","name":"\u0418\u0433\u043e\u0440\u044c \u0421\u043e\u0440\u043e\u043a\u043e\u043f\u0443\u0434","bib":"27126","time":"01:43:09","pace":"04:54","hometown":"\u041c\u043e\u0441\u043a\u0432\u0430, Russia","primary_bracket":"M-\u041c\u0443\u0436\u0447\u0438\u043d\u044bMALE","bracket_id":"786309","interval_id":"149013","checkpoint_id":"216049","checkpoint_name":"Finish","checkpoint_distance":"-21097","event_id":"29755"},{"id":"29443038","race_id":"73970","rank":"1872","name":"\u0412\u0430\u043b\u0435\u0440\u0438\u0439 \u0421\u0430\u0437\u043e\u043d\u043e\u0432","bib":"23883","time":"01:43:09","pace":"04:54","hometown":"\u0422\u0430\u043c\u0431\u043e\u0432, Russia","primary_bracket":"M-\u041c\u0443\u0436\u0447\u0438\u043d\u044bMALE","bracket_id":"786309","interval_id":"149013","checkpoint_id":"216049","checkpoint_name":"Finish","checkpoint_distance":"-21097","event_id":"29755"},{"id":"29443033","race_id":"73970","rank":"1873","name":"\u0410\u043b\u0435\u043a\u0441\u0435\u0439 \u0411\u044b\u043a\u043e\u0432","bib":"23882","time":"01:43:10","pace":"04:54","hometown":"\u041c\u043e\u0441\u043a\u0432\u0430, Russia","primary_bracket":"M-\u041c\u0443\u0436\u0447\u0438\u043d\u044bMALE","bracket_id":"786309","interval_id":"149013","checkpoint_id":"216049","checkpoint_name":"Finish","checkpoint_distance":"-21097","event_id":"29755"},{"id":"29443028","race_id":"73970","rank":"1874","name":"\u041e\u043b\u0435\u0433 \u0427\u0443\u043a\u0438\u043d","bib":"23881","time":"01:43:10","pace":"04:54","hometown":"\u041c\u043e\u0441\u043a\u0432\u0430, Russia","primary_bracket":"M-\u041c\u0443\u0436\u0447\u0438\u043d\u044bMALE","bracket_id":"786309","interval_id":"149013","checkpoint_id":"216049","checkpoint_name":"Finish","checkpoint_distance":"-21097","event_id":"29755"},{"id":"29443419","race_id":"73970","rank":"1875","name":"Denis Pantyukhin","bib":"27067","time":"01:43:10","pace":"04:54","hometown":"\u041c\u043e\u0441\u043a\u0432\u0430, Russia","primary_bracket":"M-\u041c\u0443\u0436\u0447\u0438\u043d\u044bMALE","bracket_id":"786309","interval_id":"149013","checkpoint_id":"216049","checkpoint_name":"Finish","checkpoint_distance":"-21097","event_id":"29755"},{"id":"29442215","race_id":"73970","rank":"1876","name":"Ksenia Kuznetsova","bib":"20788","time":"01:43:11","pace":"04:54","hometown":"\u041c\u043e\u0441\u043a\u0432\u0430, Russia","primary_bracket":"F-\u0416\u0435\u043d\u0449\u0438\u043d\u044bFEMALE","bracket_id":"786309","interval_id":"149013","checkpoint_id":"216049","checkpoint_name":"Finish","checkpoint_distance":"-21097","event_id":"29755"},{"id":"29440233","race_id":"73970","rank":"1877","name":"\u0410\u043b\u0435\u043a\u0441\u0430\u043d\u0434\u0440 \u041c\u0430\u043b\u044b\u0445","bib":"20319","time":"01:43:11","pace":"04:54","hometown":"\u0418\u0436\u0435\u0432\u0441\u043a, Russia","primary_bracket":"M-\u041c\u0443\u0436\u0447\u0438\u043d\u044bMALE","bracket_id":"786309","interval_id":"149013","checkpoint_id":"216049","checkpoint_name":"Finish","checkpoint_distance":"-21097","event_id":"29755"},{"id":"29444993","race_id":"73970","rank":"1878","name":"\u0410\u043b\u0435\u043a\u0441\u0435\u0439 \u041a\u043e\u043b\u0435\u0441\u043d\u0438\u043a\u043e\u0432","bib":"25804","time":"01:43:11","pace":"04:54","hometown":"\u041c\u043e\u0441\u043a\u0432\u0430, Russia","primary_bracket":"M-\u041c\u0443\u0436\u0447\u0438\u043d\u044bMALE","bracket_id":"786309","interval_id":"149013","checkpoint_id":"216049","checkpoint_name":"Finish","checkpoint_distance":"-21097","event_id":"29755"},{"id":"29440877","race_id":"73970","rank":"1879","name":"\u041a\u043e\u043d\u0441\u0442\u0430\u043d\u0442\u0438\u043d \u0421\u0430\u0440\u0430\u0435\u0432","bib":"20471","time":"01:43:11","pace":"04:54","hometown":"\u041c\u043e\u0441\u043a\u0432\u0430, Russia","primary_bracket":"M-\u041c\u0443\u0436\u0447\u0438\u043d\u044bMALE","bracket_id":"786309","interval_id":"149013","checkpoint_id":"216049","checkpoint_name":"Finish","checkpoint_distance":"-21097","event_id":"29755"},{"id":"29440135","race_id":"73970","rank":"1880","name":"\u0414\u043c\u0438\u0442\u0440\u0438\u0439 \u0411\u0435\u043b\u043e\u0432","bib":"24883","time":"01:43:12","pace":"04:54","hometown":"\u041c\u043e\u0441\u043a\u0432\u0430, Russia","primary_bracket":"M-\u041c\u0443\u0436\u0447\u0438\u043d\u044bMALE","bracket_id":"786309","interval_id":"149013","checkpoint_id":"216049","checkpoint_name":"Finish","checkpoint_distance":"-21097","event_id":"29755"},{"id":"29444559","race_id":"73970","rank":"1881","name":"\u0413\u0435\u043e\u0440\u0433\u0438\u0439 \u0421\u043b\u0443\u0433\u0438\u043d","bib":"27288","time":"01:43:13","pace":"04:54","hometown":"\u041c\u043e\u0441\u043a\u0432\u0430, Russia","primary_bracket":"M-\u041c\u0443\u0436\u0447\u0438\u043d\u044bMALE","bracket_id":"786309","interval_id":"149013","checkpoint_id":"216049","checkpoint_name":"Finish","checkpoint_distance":"-21097","event_id":"29755"},{"id":"29444443","race_id":"73970","rank":"1882","name":"\u0416\u0435\u043d\u044f \u0413\u0443\u0440\u0432\u0438\u0447","bib":"27266","time":"01:43:14","pace":"04:54","hometown":"\u041c\u043e\u0441\u043a\u0432\u0430, Russia","primary_bracket":"M-\u041c\u0443\u0436\u0447\u0438\u043d\u044bMALE","bracket_id":"786309","interval_id":"149013","checkpoint_id":"216049","checkpoint_name":"Finish","checkpoint_distance":"-21097","event_id":"29755"},{"id":"29440645","race_id":"73970","rank":"1883","name":"\u0410\u043b\u0435\u043a\u0441\u0430\u043d\u0434\u0440 \u041a\u0443\u0447\u0435\u0440\u0430","bib":"23428","time":"01:43:14","pace":"04:54","hometown":"\u041c\u043e\u0441\u043a\u0432\u0430, Russia","primary_bracket":"M-\u041c\u0443\u0436\u0447\u0438\u043d\u044bMALE","bracket_id":"786309","interval_id":"149013","checkpoint_id":"216049","checkpoint_name":"Finish","checkpoint_distance":"-21097","event_id":"29755"},{"id":"29438961","race_id":"73970","rank":"1884","name":"\u0414\u043c\u0438\u0442\u0440\u0438\u0439 \u0410\u043d\u0434\u0440\u0438\u0430\u043d\u043e\u0432","bib":"21561","time":"01:43:15","pace":"04:54","hometown":"\u041c\u0443\u0440\u043e\u043c, Russia","primary_bracket":"M-\u041c\u0443\u0436\u0447\u0438\u043d\u044bMALE","bracket_id":"786309","interval_id":"149013","checkpoint_id":"216049","checkpoint_name":"Finish","checkpoint_distance":"-21097","event_id":"29755"},{"id":"29440456","race_id":"73970","rank":"1885","name":"Andrey Chernuha","bib":"23392","time":"01:43:15","pace":"04:54","hometown":"\u041c\u043e\u0441\u043a\u0432\u0430, Russia","primary_bracket":"M-\u041c\u0443\u0436\u0447\u0438\u043d\u044bMALE","bracket_id":"786309","interval_id":"149013","checkpoint_id":"216049","checkpoint_name":"Finish","checkpoint_distance":"-21097","event_id":"29755"},{"id":"29446528","race_id":"73970","rank":"1886","name":"\u0412\u0438\u043a\u0442\u043e\u0440 \u0414\u0435\u0440\u0435\u0432\u044f\u0433\u0438\u043d","bib":"26157","time":"01:43:16","pace":"04:54","hometown":"\u041c\u043e\u0441\u043a\u0432\u0430, Russia","primary_bracket":"M-\u041c\u0443\u0436\u0447\u0438\u043d\u044bMALE","bracket_id":"786309","interval_id":"149013","checkpoint_id":"216049","checkpoint_name":"Finish","checkpoint_distance":"-21097","event_id":"29755"},{"id":"29591649","race_id":"73970","rank":"1887","name":"\u0421\u0435\u0440\u0433\u0435\u0439 \u041a\u043e\u0432\u0430\u043b\u0435\u0432","bib":"28136","time":"01:43:16","pace":"04:54","hometown":"\u041c\u043e\u0441\u043a\u0432\u0430, Russia","primary_bracket":"M-\u041c\u0443\u0436\u0447\u0438\u043d\u044bMALE","bracket_id":"786309","interval_id":"149013","checkpoint_id":"216049","checkpoint_name":"Finish","checkpoint_distance":"-21097","event_id":"29755"},{"id":"29445766","race_id":"73970","rank":"1888","name":"\u0410\u043b\u0435\u043a\u0441\u0435\u0439 \u0420\u0430\u0434\u0430\u0435\u0432","bib":"27544","time":"01:43:17","pace":"04:54","hometown":"\u041c\u043e\u0441\u043a\u0432\u0430, Russia","primary_bracket":"M-\u041c\u0443\u0436\u0447\u0438\u043d\u044bMALE","bracket_id":"786309","interval_id":"149013","checkpoint_id":"216049","checkpoint_name":"Finish","checkpoint_distance":"-21097","event_id":"29755"},{"id":"29446171","race_id":"73970","rank":"1889","name":"\u0410\u043b\u0435\u043a\u0441\u0430\u043d\u0434\u0440 \u0428\u0430\u0433\u043e\u0432","bib":"27647","time":"01:43:17","pace":"04:54","hometown":"\u041c\u043e\u0441\u043a\u0432\u0430, Russia","primary_bracket":"M-\u041c\u0443\u0436\u0447\u0438\u043d\u044bMALE","bracket_id":"786309","interval_id":"149013","checkpoint_id":"216049","checkpoint_name":"Finish","checkpoint_distance":"-21097","event_id":"29755"},{"id":"29444307","race_id":"73970","rank":"1890","name":"Ilya Sovtsov","bib":"21290","time":"01:43:17","pace":"04:54","hometown":"\u041c\u043e\u0441\u043a\u0432\u0430, Russia","primary_bracket":"M-\u041c\u0443\u0436\u0447\u0438\u043d\u044bMALE","bracket_id":"786309","interval_id":"149013","checkpoint_id":"216049","checkpoint_name":"Finish","checkpoint_distance":"-21097","event_id":"29755"},{"id":"29443079","race_id":"73970","rank":"1891","name":"Patrick Ghidirim","bib":"23891","time":"01:43:19","pace":"04:54","hometown":"\u041c\u043e\u0441\u043a\u0432\u0430, Russia","primary_bracket":"M-\u041c\u0443\u0436\u0447\u0438\u043d\u044bMALE","bracket_id":"786309","interval_id":"149013","checkpoint_id":"216049","checkpoint_name":"Finish","checkpoint_distance":"-21097","event_id":"29755"},{"id":"29443467","race_id":"73970","rank":"1892","name":"\u041c\u0438\u0445\u0430\u0438\u043b \u0425\u0430\u0440\u043b\u0430\u043c\u043e\u0432","bib":"22412","time":"01:43:19","pace":"04:54","hometown":"\u041c\u043e\u0441\u043a\u0432\u0430, Russia","primary_bracket":"M-\u041c\u0443\u0436\u0447\u0438\u043d\u044bMALE","bracket_id":"786309","interval_id":"149013","checkpoint_id":"216049","checkpoint_name":"Finish","checkpoint_distance":"-21097","event_id":"29755"},{"id":"29444982","race_id":"73970","rank":"1893","name":"Alexander Gavrilyuk","bib":"25802","time":"01:43:19","pace":"04:54","hometown":"\u041c\u043e\u0441\u043a\u0432\u0430, Russia","primary_bracket":"M-\u041c\u0443\u0436\u0447\u0438\u043d\u044bMALE","bracket_id":"786309","interval_id":"149013","checkpoint_id":"216049","checkpoint_name":"Finish","checkpoint_distance":"-21097","event_id":"29755"},{"id":"29446403","race_id":"73970","rank":"1894","name":"\u0414\u043c\u0438\u0442\u0440\u0438\u0439 \u0413\u043e\u0432\u043e\u0440\u0443\u0445\u0430","bib":"26126","time":"01:43:19","pace":"04:54","hometown":"\u041c\u043e\u0441\u043a\u0432\u0430, Russia","primary_bracket":"M-\u041c\u0443\u0436\u0447\u0438\u043d\u044bMALE","bracket_id":"786309","interval_id":"149013","checkpoint_id":"216049","checkpoint_name":"Finish","checkpoint_distance":"-21097","event_id":"29755"},{"id":"29570968","race_id":"73970","rank":"1895","name":"\u0415\u0433\u043e\u0440 \u0410\u043d\u0438\u0441\u0438\u043c\u043e\u0432","bib":"27935","time":"01:43:19","pace":"04:54","hometown":"\u041d\u043e\u0432\u0430\u044f \u0423\u0441\u043c\u0430\u043d\u044c, Russia","primary_bracket":"M-\u041c\u0443\u0436\u0447\u0438\u043d\u044bMALE","bracket_id":"786309","interval_id":"149013","checkpoint_id":"216049","checkpoint_name":"Finish","checkpoint_distance":"-21097","event_id":"29755"},{"id":"29442725","race_id":"73970","rank":"1896","name":"\u0414\u043c\u0438\u0442\u0440\u0438\u0439 \u0427\u0435\u0440\u043d\u0443\u0445\u0438\u043d","bib":"22272","time":"01:43:20","pace":"04:54","hometown":"\u041c\u043e\u0441\u043a\u0432\u0430, Russia","primary_bracket":"M-\u041c\u0443\u0436\u0447\u0438\u043d\u044bMALE","bracket_id":"786309","interval_id":"149013","checkpoint_id":"216049","checkpoint_name":"Finish","checkpoint_distance":"-21097","event_id":"29755"},{"id":"29445733","race_id":"73970","rank":"1897","name":"\u041a\u0438\u0440\u0438\u043b\u043b \u041d\u0430\u043a\u0430\u043f\u043a\u0438\u043d","bib":"22863","time":"01:43:20","pace":"04:54","hometown":"\u041c\u043e\u0441\u043a\u0432\u0430, Russia","primary_bracket":"M-\u041c\u0443\u0436\u0447\u0438\u043d\u044bMALE","bracket_id":"786309","interval_id":"149013","checkpoint_id":"216049","checkpoint_name":"Finish","checkpoint_distance":"-21097","event_id":"29755"},{"id":"29442363","race_id":"73970","rank":"1898","name":"\u0410\u043d\u0434\u0440\u0435\u0439 \u041b\u0430\u0442\u0440\u044b\u0433\u0438\u043d","bib":"25305","time":"01:43:20","pace":"04:54","hometown":"\u041c\u043e\u0441\u043a\u0432\u0430, Russia","primary_bracket":"M-\u041c\u0443\u0436\u0447\u0438\u043d\u044bMALE","bracket_id":"786309","interval_id":"149013","checkpoint_id":"216049","checkpoint_name":"Finish","checkpoint_distance":"-21097","event_id":"29755"},{"id":"29439808","race_id":"73970","rank":"1899","name":"\u0421\u0432\u0435\u0442\u043b\u0430\u043d\u0430 \u041a\u0430\u043d\u0442\u043e\u043d\u0438\u0441\u0442\u043e\u0432\u0430","bib":"24820","time":"01:43:20","pace":"04:54","hometown":"\u041c\u043e\u0441\u043a\u0432\u0430, Russia","primary_bracket":"F-\u0416\u0435\u043d\u0449\u0438\u043d\u044bFEMALE","bracket_id":"786309","interval_id":"149013","checkpoint_id":"216049","checkpoint_name":"Finish","checkpoint_distance":"-21097","event_id":"29755"},{"id":"29440189","race_id":"73970","rank":"1900","name":"Yury Konovalov","bib":"23341","time":"01:43:21","pace":"04:54","hometown":"\u041c\u043e\u0441\u043a\u0432\u0430, Russia","primary_bracket":"M-\u041c\u0443\u0436\u0447\u0438\u043d\u044bMALE","bracket_id":"786309","interval_id":"149013","checkpoint_id":"216049","checkpoint_name":"Finish","checkpoint_distance":"-21097","event_id":"29755"}]}