{"total":"7173","results":[{"id":"29444447","race_id":"73970","rank":"6401","name":"Emma Nottingham","bib":"21323","time":"02:19:00","pace":"06:36","hometown":"\u041c\u043e\u0441\u043a\u0432\u0430, Russia","primary_bracket":"F-\u0416\u0435\u043d\u0449\u0438\u043d\u044bFEMALE","bracket_id":"786309","interval_id":"149013","checkpoint_id":"216049","checkpoint_name":"Finish","checkpoint_distance":"-21097","event_id":"29755"},{"id":"29439699","race_id":"73970","rank":"6402","name":"\u0415\u043a\u0430\u0442\u0435\u0440\u0438\u043d\u0430 \u0422\u0438\u043c\u043e\u0448\u0438\u043d\u0430","bib":"26348","time":"02:19:00","pace":"06:36","hometown":"\u041d\u0430\u0440\u043e-\u0424\u043e\u043c\u0438\u043d\u0441\u043a, Russia","primary_bracket":"F-\u0416\u0435\u043d\u0449\u0438\u043d\u044bFEMALE","bracket_id":"786309","interval_id":"149013","checkpoint_id":"216049","checkpoint_name":"Finish","checkpoint_distance":"-21097","event_id":"29755"},{"id":"29442383","race_id":"73970","rank":"6403","name":"Alexandra Zhukova","bib":"22208","time":"02:19:00","pace":"06:36","hometown":"\u041c\u043e\u0441\u043a\u0432\u0430, Russia","primary_bracket":"F-\u0416\u0435\u043d\u0449\u0438\u043d\u044bFEMALE","bracket_id":"786309","interval_id":"149013","checkpoint_id":"216049","checkpoint_name":"Finish","checkpoint_distance":"-21097","event_id":"29755"},{"id":"29444523","race_id":"73970","rank":"6404","name":"\u0410\u043b\u0438\u043d\u0430 \u0411\u043e\u0440\u043e\u0434\u0438\u043d\u0430","bib":"27281","time":"02:19:00","pace":"06:36","hometown":"\u041c\u043e\u0441\u043a\u0432\u0430, Russia","primary_bracket":"F-\u0416\u0435\u043d\u0449\u0438\u043d\u044bFEMALE","bracket_id":"786309","interval_id":"149013","checkpoint_id":"216049","checkpoint_name":"Finish","checkpoint_distance":"-21097","event_id":"29755"},{"id":"29571074","race_id":"73970","rank":"6405","name":"\u0415\u043a\u0430\u0442\u0435\u0440\u0438\u043d\u0430 \u041f\u043e\u043d\u043e\u043c\u0430\u0440\u0435\u043d\u043a\u043e","bib":"27776","time":"02:19:01","pace":"06:36","hometown":"\u041c\u043e\u0441\u043a\u0432\u0430, Russia","primary_bracket":"F-\u0416\u0435\u043d\u0449\u0438\u043d\u044bFEMALE","bracket_id":"786309","interval_id":"149013","checkpoint_id":"216049","checkpoint_name":"Finish","checkpoint_distance":"-21097","event_id":"29755"},{"id":"29442536","race_id":"73970","rank":"6406","name":"\u0410\u043b\u0435\u043a\u0441\u0435\u0439 \u0415\u0440\u043e\u0448\u0435\u043d\u043a\u043e","bib":"25337","time":"02:19:01","pace":"06:36","hometown":"\u041c\u043e\u0441\u043a\u0432\u0430, Russia","primary_bracket":"M-\u041c\u0443\u0436\u0447\u0438\u043d\u044bMALE","bracket_id":"786309","interval_id":"149013","checkpoint_id":"216049","checkpoint_name":"Finish","checkpoint_distance":"-21097","event_id":"29755"},{"id":"29441846","race_id":"73970","rank":"6407","name":"\u0410\u043d\u043d\u0430 \u0411\u0430\u0440\u0445\u0430\u0442\u043e\u0432\u0430","bib":"20701","time":"02:19:02","pace":"06:36","hometown":"\u041c\u043e\u0441\u043a\u0432\u0430, Russia","primary_bracket":"F-\u0416\u0435\u043d\u0449\u0438\u043d\u044bFEMALE","bracket_id":"786309","interval_id":"149013","checkpoint_id":"216049","checkpoint_name":"Finish","checkpoint_distance":"-21097","event_id":"29755"},{"id":"29441173","race_id":"73970","rank":"6408","name":"\u042e\u0440\u0438\u0439 \u0421\u043a\u0440\u0438\u043f\u0441\u0442","bib":"21977","time":"02:19:08","pace":"06:36","hometown":"\u041c\u043e\u0441\u043a\u0432\u0430, Russia","primary_bracket":"M-\u041c\u0443\u0436\u0447\u0438\u043d\u044bMALE","bracket_id":"786309","interval_id":"149013","checkpoint_id":"216049","checkpoint_name":"Finish","checkpoint_distance":"-21097","event_id":"29755"},{"id":"29440762","race_id":"73970","rank":"6409","name":"\u0412\u0430\u0441\u0438\u043b\u0438\u0439 \u041a\u0443\u0437\u043d\u0435\u0446\u043e\u0432","bib":"26553","time":"02:19:09","pace":"06:36","hometown":"\u041c\u043e\u0441\u043a\u0432\u0430, Russia","primary_bracket":"M-\u041c\u0443\u0436\u0447\u0438\u043d\u044bMALE","bracket_id":"786309","interval_id":"149013","checkpoint_id":"216049","checkpoint_name":"Finish","checkpoint_distance":"-21097","event_id":"29755"},{"id":"29442896","race_id":"73970","rank":"6410","name":"\u0410\u043d\u043d\u0430 \u0422\u0430\u043c\u0431\u043e\u0432\u0446\u0435\u0432\u0430","bib":"20954","time":"02:19:09","pace":"06:36","hometown":"\u041c\u043e\u0441\u043a\u0432\u0430, Russia","primary_bracket":"F-\u0416\u0435\u043d\u0449\u0438\u043d\u044bFEMALE","bracket_id":"786309","interval_id":"149013","checkpoint_id":"216049","checkpoint_name":"Finish","checkpoint_distance":"-21097","event_id":"29755"},{"id":"29442887","race_id":"73970","rank":"6411","name":"Marta Kanafockaya","bib":"25403","time":"02:19:11","pace":"06:36","hometown":"\u041c\u043e\u0441\u043a\u0432\u0430, Russia","primary_bracket":"F-\u0416\u0435\u043d\u0449\u0438\u043d\u044bFEMALE","bracket_id":"786309","interval_id":"149013","checkpoint_id":"216049","checkpoint_name":"Finish","checkpoint_distance":"-21097","event_id":"29755"},{"id":"29441394","race_id":"73970","rank":"6412","name":"\u041e\u043b\u0435\u0433 \u041d\u043e\u0432\u0438\u043a\u043e\u0432","bib":"23570","time":"02:19:11","pace":"06:36","hometown":"\u041c\u043e\u0441\u043a\u0432\u0430, Russia","primary_bracket":"M-\u041c\u0443\u0436\u0447\u0438\u043d\u044bMALE","bracket_id":"786309","interval_id":"149013","checkpoint_id":"216049","checkpoint_name":"Finish","checkpoint_distance":"-21097","event_id":"29755"},{"id":"29446485","race_id":"73970","rank":"6413","name":"Olga Turevich","bib":"24603","time":"02:19:11","pace":"06:36","hometown":"\u041c\u043e\u0441\u043a\u0432\u0430, Russia","primary_bracket":"F-\u0416\u0435\u043d\u0449\u0438\u043d\u044bFEMALE","bracket_id":"786309","interval_id":"149013","checkpoint_id":"216049","checkpoint_name":"Finish","checkpoint_distance":"-21097","event_id":"29755"},{"id":"29591672","race_id":"73970","rank":"6414","name":"\u0415\u043a\u0430\u0442\u0435\u0440\u0438\u043d\u0430 \u0414\u0435\u043c\u0438\u0434\u0435\u043d\u043a\u043e","bib":"28128","time":"02:19:11","pace":"06:36","hometown":"\u041c\u043e\u0441\u043a\u0432\u0430, Russia","primary_bracket":"F-\u0416\u0435\u043d\u0449\u0438\u043d\u044bFEMALE","bracket_id":"786309","interval_id":"149013","checkpoint_id":"216049","checkpoint_name":"Finish","checkpoint_distance":"-21097","event_id":"29755"},{"id":"29439823","race_id":"73970","rank":"6415","name":"\u0412\u043b\u0430\u0434\u0438\u043c\u0438\u0440 \u041f\u043e\u0434\u043b\u0435\u0441\u043d\u044b\u0439","bib":"23271","time":"02:19:12","pace":"06:36","hometown":"\u041c\u043e\u0441\u043a\u0432\u0430, Russia","primary_bracket":"M-\u041c\u0443\u0436\u0447\u0438\u043d\u044bMALE","bracket_id":"786309","interval_id":"149013","checkpoint_id":"216049","checkpoint_name":"Finish","checkpoint_distance":"-21097","event_id":"29755"},{"id":"29441749","race_id":"73970","rank":"6416","name":"\u0415\u043b\u0435\u043d\u0430 \u0412\u0435\u0448\u0442\u043e\u0440\u0442","bib":"25189","time":"02:19:12","pace":"06:36","hometown":"\u041c\u043e\u0441\u043a\u0432\u0430, Russia","primary_bracket":"F-\u0416\u0435\u043d\u0449\u0438\u043d\u044bFEMALE","bracket_id":"786309","interval_id":"149013","checkpoint_id":"216049","checkpoint_name":"Finish","checkpoint_distance":"-21097","event_id":"29755"},{"id":"29446557","race_id":"73970","rank":"6417","name":"\u0421\u0435\u0440\u0433\u0435\u0439 \u041e\u043b\u0435\u0439\u043d\u0438\u043a","bib":"24621","time":"02:19:15","pace":"06:36","hometown":"\u041c\u043e\u0441\u043a\u0432\u0430, Russia","primary_bracket":"M-\u041c\u0443\u0436\u0447\u0438\u043d\u044bMALE","bracket_id":"786309","interval_id":"149013","checkpoint_id":"216049","checkpoint_name":"Finish","checkpoint_distance":"-21097","event_id":"29755"},{"id":"29442670","race_id":"73970","rank":"6418","name":"\u0414\u043c\u0438\u0442\u0440\u0438\u0439 \u0415\u0441\u044c\u043a\u0438\u043d","bib":"20898","time":"02:19:16","pace":"06:37","hometown":"\u041c\u043e\u0441\u043a\u0432\u0430, Russia","primary_bracket":"M-\u041c\u0443\u0436\u0447\u0438\u043d\u044bMALE","bracket_id":"786309","interval_id":"149013","checkpoint_id":"216049","checkpoint_name":"Finish","checkpoint_distance":"-21097","event_id":"29755"},{"id":"29571003","race_id":"73970","rank":"6419","name":"\u0421\u0432\u0435\u0442\u043b\u0430\u043d\u0430 \u041f\u043e\u043f\u043e\u0432\u0430","bib":"27801","time":"02:19:18","pace":"06:37","hometown":"\u041c\u043e\u0441\u043a\u0432\u0430, Russia","primary_bracket":"F-\u0416\u0435\u043d\u0449\u0438\u043d\u044bFEMALE","bracket_id":"786309","interval_id":"149013","checkpoint_id":"216049","checkpoint_name":"Finish","checkpoint_distance":"-21097","event_id":"29755"},{"id":"29591455","race_id":"73970","rank":"6420","name":"\u0410\u043d\u0434\u0440\u0435\u0439 \u041d\u043e\u0441\u043e\u0432","bib":"28201","time":"02:19:18","pace":"06:37","hometown":"\u041c\u043e\u0441\u043a\u0432\u0430, Russia","primary_bracket":"M-\u041c\u0443\u0436\u0447\u0438\u043d\u044bMALE","bracket_id":"786309","interval_id":"149013","checkpoint_id":"216049","checkpoint_name":"Finish","checkpoint_distance":"-21097","event_id":"29755"},{"id":"29444924","race_id":"73970","rank":"6421","name":"Alexandra Kremenets","bib":"22688","time":"02:19:19","pace":"06:37","hometown":"\u041c\u043e\u0441\u043a\u0432\u0430, Russia","primary_bracket":"F-\u0416\u0435\u043d\u0449\u0438\u043d\u044bFEMALE","bracket_id":"786309","interval_id":"149013","checkpoint_id":"216049","checkpoint_name":"Finish","checkpoint_distance":"-21097","event_id":"29755"},{"id":"29445837","race_id":"73970","rank":"6422","name":"\u0410\u043d\u0434\u0440\u0435\u0439 \u0411\u0430\u0441\u0430\u043b\u044b\u0433\u0430","bib":"27562","time":"02:19:20","pace":"06:37","hometown":"\u041c\u043e\u0441\u043a\u0432\u0430, Russia","primary_bracket":"M-\u041c\u0443\u0436\u0447\u0438\u043d\u044bMALE","bracket_id":"786309","interval_id":"149013","checkpoint_id":"216049","checkpoint_name":"Finish","checkpoint_distance":"-21097","event_id":"29755"},{"id":"29443475","race_id":"73970","rank":"6423","name":"\u0415\u043a\u0430\u0442\u0435\u0440\u0438\u043d\u0430 \u0415\u043f\u0438\u0445\u0438\u043d\u0430","bib":"21091","time":"02:19:20","pace":"06:37","hometown":"\u041c\u043e\u0441\u043a\u0432\u0430, Russia","primary_bracket":"F-\u0416\u0435\u043d\u0449\u0438\u043d\u044bFEMALE","bracket_id":"786309","interval_id":"149013","checkpoint_id":"216049","checkpoint_name":"Finish","checkpoint_distance":"-21097","event_id":"29755"},{"id":"29443022","race_id":"73970","rank":"6424","name":"\u042e\u0440\u0438\u0439 \u041a\u043e\u0442\u043e\u0432\u0441\u043a\u0438\u0439","bib":"20984","time":"02:19:21","pace":"06:37","hometown":"\u041c\u043e\u0441\u043a\u0432\u0430, Russia","primary_bracket":"M-\u041c\u0443\u0436\u0447\u0438\u043d\u044bMALE","bracket_id":"786309","interval_id":"149013","checkpoint_id":"216049","checkpoint_name":"Finish","checkpoint_distance":"-21097","event_id":"29755"},{"id":"29571133","race_id":"73970","rank":"6425","name":"\u0410\u043d\u0430\u0442\u043e\u043b\u0438\u0439 \u0411\u0430\u0441\u0430\u043b\u044b\u0433\u0430","bib":"27881","time":"02:19:21","pace":"06:37","hometown":"\u041c\u043e\u0441\u043a\u0432\u0430, Russia","primary_bracket":"M-\u041c\u0443\u0436\u0447\u0438\u043d\u044bMALE","bracket_id":"786309","interval_id":"149013","checkpoint_id":"216049","checkpoint_name":"Finish","checkpoint_distance":"-21097","event_id":"29755"},{"id":"29440358","race_id":"73970","rank":"6426","name":"Christophe Feffer","bib":"24926","time":"02:19:21","pace":"06:37","hometown":"\u041c\u043e\u0441\u043a\u0432\u0430, Russia","primary_bracket":"M-\u041c\u0443\u0436\u0447\u0438\u043d\u044bMALE","bracket_id":"786309","interval_id":"149013","checkpoint_id":"216049","checkpoint_name":"Finish","checkpoint_distance":"-21097","event_id":"29755"},{"id":"29591609","race_id":"73970","rank":"6427","name":"\u0412\u0430\u0440\u0432\u0430\u0440\u0430 \u041d\u0435\u043b\u044e\u0431\u043e\u0432\u0430","bib":"28149","time":"02:19:22","pace":"06:37","hometown":"\u041c\u043e\u0441\u043a\u0432\u0430, Russia","primary_bracket":"F-\u0416\u0435\u043d\u0449\u0438\u043d\u044bFEMALE","bracket_id":"786309","interval_id":"149013","checkpoint_id":"216049","checkpoint_name":"Finish","checkpoint_distance":"-21097","event_id":"29755"},{"id":"29440256","race_id":"73970","rank":"6428","name":"\u0421\u0435\u0440\u0433\u0435\u0439 \u041a\u0443\u0437\u0435\u043d\u043a\u043e\u0432","bib":"24906","time":"02:19:23","pace":"06:37","hometown":"\u041c\u043e\u0441\u043a\u0432\u0430, Russia","primary_bracket":"M-\u041c\u0443\u0436\u0447\u0438\u043d\u044bMALE","bracket_id":"786309","interval_id":"149013","checkpoint_id":"216049","checkpoint_name":"Finish","checkpoint_distance":"-21097","event_id":"29755"},{"id":"29442716","race_id":"73970","rank":"6429","name":"\u0415\u043b\u0435\u043d\u0430 \u0414\u0443\u043c\u0435\u043d\u043a\u043e\u0432\u0430","bib":"23822","time":"02:19:23","pace":"06:37","hometown":"\u041c\u043e\u0441\u043a\u0432\u0430, Russia","primary_bracket":"F-\u0416\u0435\u043d\u0449\u0438\u043d\u044bFEMALE","bracket_id":"786309","interval_id":"149013","checkpoint_id":"216049","checkpoint_name":"Finish","checkpoint_distance":"-21097","event_id":"29755"},{"id":"29445748","race_id":"73970","rank":"6430","name":"Vitaly Chelochev","bib":"24418","time":"02:19:23","pace":"06:37","hometown":"\u041c\u043e\u0441\u043a\u0432\u0430, Russia","primary_bracket":"M-\u041c\u0443\u0436\u0447\u0438\u043d\u044bMALE","bracket_id":"786309","interval_id":"149013","checkpoint_id":"216049","checkpoint_name":"Finish","checkpoint_distance":"-21097","event_id":"29755"},{"id":"29570810","race_id":"73970","rank":"6431","name":"\u0418\u0440\u0438\u043d\u0430 \u041c\u0430\u043a\u0430\u0440\u043e\u0432\u0430","bib":"28113","time":"02:19:23","pace":"06:37","hometown":"\u041c\u043e\u0441\u043a\u0432\u0430, Russia","primary_bracket":"F-\u0416\u0435\u043d\u0449\u0438\u043d\u044bFEMALE","bracket_id":"786309","interval_id":"149013","checkpoint_id":"216049","checkpoint_name":"Finish","checkpoint_distance":"-21097","event_id":"29755"},{"id":"29443307","race_id":"73970","rank":"6432","name":"\u0414\u043c\u0438\u0442\u0440\u0438\u0439 \u0413\u0430\u043b\u044c\u0446\u0435\u0432","bib":"25483","time":"02:19:26","pace":"06:37","hometown":"\u041c\u043e\u0441\u043a\u0432\u0430, Russia","primary_bracket":"M-\u041c\u0443\u0436\u0447\u0438\u043d\u044bMALE","bracket_id":"786309","interval_id":"149013","checkpoint_id":"216049","checkpoint_name":"Finish","checkpoint_distance":"-21097","event_id":"29755"},{"id":"29439576","race_id":"73970","rank":"6433","name":"\u0415\u043a\u0430\u0442\u0435\u0440\u0438\u043d\u0430 \u041b\u044e\u0434\u043a\u043e\u0432\u0430","bib":"24776","time":"02:19:26","pace":"06:37","hometown":"\u041c\u043e\u0441\u043a\u0432\u0430, Russia","primary_bracket":"F-\u0416\u0435\u043d\u0449\u0438\u043d\u044bFEMALE","bracket_id":"786309","interval_id":"149013","checkpoint_id":"216049","checkpoint_name":"Finish","checkpoint_distance":"-21097","event_id":"29755"},{"id":"29439413","race_id":"73970","rank":"6434","name":"Oleg Ivchenko","bib":"20125","time":"02:19:27","pace":"06:37","hometown":"\u041c\u043e\u0441\u043a\u0432\u0430, Russia","primary_bracket":"M-\u041c\u0443\u0436\u0447\u0438\u043d\u044bMALE","bracket_id":"786309","interval_id":"149013","checkpoint_id":"216049","checkpoint_name":"Finish","checkpoint_distance":"-21097","event_id":"29755"},{"id":"29442121","race_id":"73970","rank":"6435","name":"\u0410\u043d\u0434\u0440\u0435\u0439 \u041b\u0443\u043a\u0443\u0442\u043a\u0438\u043d","bib":"23709","time":"02:19:27","pace":"06:37","hometown":"\u0414\u0423\u0411\u041d\u0410, Russia","primary_bracket":"M-\u041c\u0443\u0436\u0447\u0438\u043d\u044bMALE","bracket_id":"786309","interval_id":"149013","checkpoint_id":"216049","checkpoint_name":"Finish","checkpoint_distance":"-21097","event_id":"29755"},{"id":"29445000","race_id":"73970","rank":"6436","name":"Anna Skorolupova","bib":"21455","time":"02:19:28","pace":"06:37","hometown":"\u041c\u043e\u0441\u043a\u0432\u0430, Russia","primary_bracket":"F-\u0416\u0435\u043d\u0449\u0438\u043d\u044bFEMALE","bracket_id":"786309","interval_id":"149013","checkpoint_id":"216049","checkpoint_name":"Finish","checkpoint_distance":"-21097","event_id":"29755"},{"id":"29444501","race_id":"73970","rank":"6437","name":"\u0413\u0435\u043e\u0440\u0433\u0438\u0439 \u041a\u0440\u044e\u0447\u043a\u043e\u0432","bib":"21336","time":"02:19:28","pace":"06:37","hometown":"\u041c\u043e\u0441\u043a\u0432\u0430, Russia","primary_bracket":"M-\u041c\u0443\u0436\u0447\u0438\u043d\u044bMALE","bracket_id":"786309","interval_id":"149013","checkpoint_id":"216049","checkpoint_name":"Finish","checkpoint_distance":"-21097","event_id":"29755"},{"id":"29440868","race_id":"73970","rank":"6438","name":"\u0418\u0433\u043e\u0440\u044c \u041a\u043e\u043d\u043d\u043e\u0432","bib":"20469","time":"02:19:33","pace":"06:37","hometown":"\u0411\u0435\u043b\u0433\u043e\u0440\u043e\u0434, Russia","primary_bracket":"M-\u041c\u0443\u0436\u0447\u0438\u043d\u044bMALE","bracket_id":"786309","interval_id":"149013","checkpoint_id":"216049","checkpoint_name":"Finish","checkpoint_distance":"-21097","event_id":"29755"},{"id":"29445321","race_id":"73970","rank":"6439","name":"\u0418\u0443\u043b\u0438\u044f \u0411\u0435\u043b\u043e\u0448\u0430\u043f\u043a\u0430","bib":"25862","time":"02:19:34","pace":"06:37","hometown":"\u041c\u043e\u0441\u043a\u0432\u0430, Russia","primary_bracket":"F-\u0416\u0435\u043d\u0449\u0438\u043d\u044bFEMALE","bracket_id":"786309","interval_id":"149013","checkpoint_id":"216049","checkpoint_name":"Finish","checkpoint_distance":"-21097","event_id":"29755"},{"id":"29445252","race_id":"73970","rank":"6440","name":"\u0410\u043d\u0430\u0441\u0442\u0430\u0441\u0438\u044f \u041b\u043e\u0441\u043a\u0443\u0442\u043e\u0432\u0430","bib":"22752","time":"02:19:34","pace":"06:37","hometown":"\u0412\u0421\u0415\u0412\u041e\u041b\u041e\u0416\u0421\u041a, Russia","primary_bracket":"F-\u0416\u0435\u043d\u0449\u0438\u043d\u044bFEMALE","bracket_id":"786309","interval_id":"149013","checkpoint_id":"216049","checkpoint_name":"Finish","checkpoint_distance":"-21097","event_id":"29755"},{"id":"29445005","race_id":"73970","rank":"6441","name":"\u0410\u043d\u0430\u0441\u0442\u0430\u0441\u0438\u044f \u041a\u0443\u0440\u0430\u0447\u0435\u043d\u043a\u043e","bib":"22703","time":"02:19:35","pace":"06:37","hometown":"\u041c\u043e\u0441\u043a\u0432\u0430, Russia","primary_bracket":"F-\u0416\u0435\u043d\u0449\u0438\u043d\u044bFEMALE","bracket_id":"786309","interval_id":"149013","checkpoint_id":"216049","checkpoint_name":"Finish","checkpoint_distance":"-21097","event_id":"29755"},{"id":"29446510","race_id":"73970","rank":"6442","name":"\u0421\u0435\u0440\u0433\u0435\u0439 \u0420\u0430\u0442\u0443\u0448\u043d\u044f\u043a","bib":"23055","time":"02:19:35","pace":"06:37","hometown":"\u041c\u043e\u0441\u043a\u0432\u0430, Russia","primary_bracket":"M-\u041c\u0443\u0436\u0447\u0438\u043d\u044bMALE","bracket_id":"786309","interval_id":"149013","checkpoint_id":"216049","checkpoint_name":"Finish","checkpoint_distance":"-21097","event_id":"29755"},{"id":"29445324","race_id":"73970","rank":"6443","name":"\u0410\u043b\u0435\u043a\u0441\u0430\u043d\u0434\u0440 \u041c\u0430\u043a\u0430\u0440\u0435\u043d\u043a\u043e\u0432","bib":"22766","time":"02:19:36","pace":"06:38","hometown":"\u041c\u043e\u0441\u043a\u0432\u0430, Russia","primary_bracket":"M-\u041c\u0443\u0436\u0447\u0438\u043d\u044bMALE","bracket_id":"786309","interval_id":"149013","checkpoint_id":"216049","checkpoint_name":"Finish","checkpoint_distance":"-21097","event_id":"29755"},{"id":"29439669","race_id":"73970","rank":"6444","name":"\u0412\u0438\u0442\u0430\u043b\u0438\u0439 \u041c\u0430\u0440\u0442\u044b\u043d\u043e\u0432","bib":"20186","time":"02:19:37","pace":"06:38","hometown":"\u041c\u043e\u0441\u043a\u0432\u0430, Russia","primary_bracket":"M-\u041c\u0443\u0436\u0447\u0438\u043d\u044bMALE","bracket_id":"786309","interval_id":"149013","checkpoint_id":"216049","checkpoint_name":"Finish","checkpoint_distance":"-21097","event_id":"29755"},{"id":"29444385","race_id":"73970","rank":"6445","name":"\u0422\u0430\u0442\u044c\u044f\u043d\u0430 \u0413\u0443\u0440\u0447\u0435\u043d\u043a\u043e","bib":"22586","time":"02:19:38","pace":"06:38","hometown":"\u041c\u043e\u0441\u043a\u0432\u0430, Russia","primary_bracket":"F-\u0416\u0435\u043d\u0449\u0438\u043d\u044bFEMALE","bracket_id":"786309","interval_id":"149013","checkpoint_id":"216049","checkpoint_name":"Finish","checkpoint_distance":"-21097","event_id":"29755"},{"id":"29442120","race_id":"73970","rank":"6446","name":"\u0412\u0430\u043b\u0435\u0440\u0438\u0439 \u0413\u0440\u0435\u0447\u0430\u043d\u044b\u0439","bib":"22159","time":"02:19:38","pace":"06:38","hometown":"\u0420\u043e\u0441\u0442\u043e\u0432-\u043d\u0430-\u0414\u043e\u043d\u0443, Russia","primary_bracket":"M-\u041c\u0443\u0436\u0447\u0438\u043d\u044bMALE","bracket_id":"786309","interval_id":"149013","checkpoint_id":"216049","checkpoint_name":"Finish","checkpoint_distance":"-21097","event_id":"29755"},{"id":"29443492","race_id":"73970","rank":"6447","name":"\u0420\u0435\u0433\u0438\u043d\u0430 \u0421\u0430\u0434\u044b\u043a\u043e\u0432\u0430","bib":"25518","time":"02:19:38","pace":"06:38","hometown":"\u041c\u043e\u0441\u043a\u0432\u0430, Russia","primary_bracket":"F-\u0416\u0435\u043d\u0449\u0438\u043d\u044bFEMALE","bracket_id":"786309","interval_id":"149013","checkpoint_id":"216049","checkpoint_name":"Finish","checkpoint_distance":"-21097","event_id":"29755"},{"id":"29443395","race_id":"73970","rank":"6448","name":"\u041f\u0430\u0432\u0435\u043b \u041a\u043b\u0435\u0439\u043c\u0435\u043d\u043e\u0432","bib":"23951","time":"02:19:38","pace":"06:38","hometown":"\u041c\u043e\u0441\u043a\u0432\u0430, Russia","primary_bracket":"M-\u041c\u0443\u0436\u0447\u0438\u043d\u044bMALE","bracket_id":"786309","interval_id":"149013","checkpoint_id":"216049","checkpoint_name":"Finish","checkpoint_distance":"-21097","event_id":"29755"},{"id":"29442377","race_id":"73970","rank":"6449","name":"\u0415\u043b\u0435\u043d\u0430 \u0414\u043c\u0438\u0442\u0440\u0438\u0435\u0432\u043d\u0430","bib":"23758","time":"02:19:39","pace":"06:38","hometown":"\u041c\u043e\u0441\u043a\u0432\u0430, Russia","primary_bracket":"F-\u0416\u0435\u043d\u0449\u0438\u043d\u044bFEMALE","bracket_id":"786309","interval_id":"149013","checkpoint_id":"216049","checkpoint_name":"Finish","checkpoint_distance":"-21097","event_id":"29755"},{"id":"29441212","race_id":"73970","rank":"6450","name":"Anastasia Astashina","bib":"26640","time":"02:19:39","pace":"06:38","hometown":"\u041c\u043e\u0441\u043a\u0432\u0430, Russia","primary_bracket":"F-\u0416\u0435\u043d\u0449\u0438\u043d\u044bFEMALE","bracket_id":"786309","interval_id":"149013","checkpoint_id":"216049","checkpoint_name":"Finish","checkpoint_distance":"-21097","event_id":"29755"},{"id":"29444587","race_id":"73970","rank":"6451","name":"\u041c\u0438\u0445\u0430\u0438\u043b \u0420\u0443\u043c\u044f\u043d\u0446\u0435\u0432","bib":"21356","time":"02:19:40","pace":"06:38","hometown":"\u041c\u043e\u0441\u043a\u0432\u0430, Russia","primary_bracket":"M-\u041c\u0443\u0436\u0447\u0438\u043d\u044bMALE","bracket_id":"786309","interval_id":"149013","checkpoint_id":"216049","checkpoint_name":"Finish","checkpoint_distance":"-21097","event_id":"29755"},{"id":"29441473","race_id":"73970","rank":"6452","name":"\u041e\u043b\u044c\u0433\u0430 \u041a\u0440\u0430\u0432\u0446\u043e\u0432\u0430","bib":"20612","time":"02:19:41","pace":"06:38","hometown":"\u041c\u043e\u0441\u043a\u0432\u0430, Russia","primary_bracket":"F-\u0416\u0435\u043d\u0449\u0438\u043d\u044bFEMALE","bracket_id":"786309","interval_id":"149013","checkpoint_id":"216049","checkpoint_name":"Finish","checkpoint_distance":"-21097","event_id":"29755"},{"id":"29440578","race_id":"73970","rank":"6453","name":"\u0414\u0430\u0440\u044c\u044f \u0413\u043b\u0430\u0434\u043a\u0438\u0445","bib":"21865","time":"02:19:41","pace":"06:38","hometown":"\u041c\u043e\u0441\u043a\u0432\u0430, Russia","primary_bracket":"F-\u0416\u0435\u043d\u0449\u0438\u043d\u044bFEMALE","bracket_id":"786309","interval_id":"149013","checkpoint_id":"216049","checkpoint_name":"Finish","checkpoint_distance":"-21097","event_id":"29755"},{"id":"29439972","race_id":"73970","rank":"6454","name":"\u0418\u0433\u043e\u0440\u044c \u041a\u0430\u043d","bib":"21751","time":"02:19:42","pace":"06:38","hometown":"\u041c\u044b\u0442\u0438\u0449\u0438, Russia","primary_bracket":"M-\u041c\u0443\u0436\u0447\u0438\u043d\u044bMALE","bracket_id":"786309","interval_id":"149013","checkpoint_id":"216049","checkpoint_name":"Finish","checkpoint_distance":"-21097","event_id":"29755"},{"id":"29444834","race_id":"73970","rank":"6455","name":"\u0415\u043b\u0435\u043d\u0430 \u0427\u0435\u0440\u043d\u043e\u0432\u0430","bib":"27341","time":"02:19:44","pace":"06:38","hometown":"\u041c\u043e\u0441\u043a\u0432\u0430, Russia","primary_bracket":"F-\u0416\u0435\u043d\u0449\u0438\u043d\u044bFEMALE","bracket_id":"786309","interval_id":"149013","checkpoint_id":"216049","checkpoint_name":"Finish","checkpoint_distance":"-21097","event_id":"29755"},{"id":"29441159","race_id":"73970","rank":"6456","name":"\u0421\u0435\u0440\u0433\u0435\u0439 \u0413\u0443\u0434\u0438\u043d","bib":"23526","time":"02:19:44","pace":"06:38","hometown":"\u041c\u043e\u0441\u043a\u0432\u0430, Russia","primary_bracket":"M-\u041c\u0443\u0436\u0447\u0438\u043d\u044bMALE","bracket_id":"786309","interval_id":"149013","checkpoint_id":"216049","checkpoint_name":"Finish","checkpoint_distance":"-21097","event_id":"29755"},{"id":"29441182","race_id":"73970","rank":"6457","name":"\u0415\u0432\u0433\u0435\u043d\u0438\u0439 \u0414\u0440\u043e\u0431\u0438\u043d\u043a\u043e","bib":"23530","time":"02:19:45","pace":"06:38","hometown":"\u041c\u043e\u0441\u043a\u0432\u0430, Russia","primary_bracket":"M-\u041c\u0443\u0436\u0447\u0438\u043d\u044bMALE","bracket_id":"786309","interval_id":"149013","checkpoint_id":"216049","checkpoint_name":"Finish","checkpoint_distance":"-21097","event_id":"29755"},{"id":"29445679","race_id":"73970","rank":"6458","name":"\u0410\u043b\u0435\u043a\u0441\u0430\u043d\u0434\u0440\u0430 \u0412\u043e\u043b\u043a\u043e\u0432\u0430","bib":"27522","time":"02:19:46","pace":"06:38","hometown":"\u041c\u043e\u0441\u043a\u0432\u0430, Russia","primary_bracket":"F-\u0416\u0435\u043d\u0449\u0438\u043d\u044bFEMALE","bracket_id":"786309","interval_id":"149013","checkpoint_id":"216049","checkpoint_name":"Finish","checkpoint_distance":"-21097","event_id":"29755"},{"id":"29445537","race_id":"73970","rank":"6459","name":"\u0414\u043c\u0438\u0442\u0440\u0438\u0439 \u0421\u0443\u0431\u0431\u043e\u0442\u0438\u043d","bib":"27486","time":"02:19:46","pace":"06:38","hometown":"\u041c\u043e\u0441\u043a\u0432\u0430, Russia","primary_bracket":"M-\u041c\u0443\u0436\u0447\u0438\u043d\u044bMALE","bracket_id":"786309","interval_id":"149013","checkpoint_id":"216049","checkpoint_name":"Finish","checkpoint_distance":"-21097","event_id":"29755"},{"id":"29441516","race_id":"73970","rank":"6460","name":"\u0415\u0432\u0433\u0435\u043d\u0438\u0439 \u0413\u043e\u0440\u0431\u0443\u043d\u043e\u0432","bib":"22043","time":"02:19:46","pace":"06:38","hometown":"\u041f\u043e\u0434\u043e\u043b\u044c\u0441\u043a, Russia","primary_bracket":"M-\u041c\u0443\u0436\u0447\u0438\u043d\u044bMALE","bracket_id":"786309","interval_id":"149013","checkpoint_id":"216049","checkpoint_name":"Finish","checkpoint_distance":"-21097","event_id":"29755"},{"id":"29570943","race_id":"73970","rank":"6461","name":"\u041b\u044e\u0434\u043c\u0438\u043b\u0430 \u041a\u0438\u0441\u0435\u043b\u0435\u0432\u0430","bib":"28068","time":"02:19:46","pace":"06:38","hometown":"\u041c\u043e\u0441\u043a\u0432\u0430, Russia","primary_bracket":"F-\u0416\u0435\u043d\u0449\u0438\u043d\u044bFEMALE","bracket_id":"786309","interval_id":"149013","checkpoint_id":"216049","checkpoint_name":"Finish","checkpoint_distance":"-21097","event_id":"29755"},{"id":"29439245","race_id":"73970","rank":"6462","name":"\u041a\u0441\u0435\u043d\u0438\u044f \u041a\u043e\u043c\u0430\u0440\u043e\u0432\u0430","bib":"20086","time":"02:19:47","pace":"06:38","hometown":"\u041c\u043e\u0441\u043a\u0432\u0430, Russia","primary_bracket":"F-\u0416\u0435\u043d\u0449\u0438\u043d\u044bFEMALE","bracket_id":"786309","interval_id":"149013","checkpoint_id":"216049","checkpoint_name":"Finish","checkpoint_distance":"-21097","event_id":"29755"},{"id":"29443915","race_id":"73970","rank":"6463","name":"\u0415\u0432\u0433\u0435\u043d\u0438\u0439 \u0421\u0435\u0440\u0433\u0435\u0435\u0432","bib":"21196","time":"02:19:47","pace":"06:38","hometown":"\u0421\u0430\u0440\u0430\u0442\u043e\u0432, Russia","primary_bracket":"M-\u041c\u0443\u0436\u0447\u0438\u043d\u044bMALE","bracket_id":"786309","interval_id":"149013","checkpoint_id":"216049","checkpoint_name":"Finish","checkpoint_distance":"-21097","event_id":"29755"},{"id":"29443665","race_id":"73970","rank":"6464","name":"Sergei Fomichev","bib":"21135","time":"02:19:47","pace":"06:38","hometown":"\u0421\u0430\u0440\u0430\u0442\u043e\u0432, Russia","primary_bracket":"M-\u041c\u0443\u0436\u0447\u0438\u043d\u044bMALE","bracket_id":"786309","interval_id":"149013","checkpoint_id":"216049","checkpoint_name":"Finish","checkpoint_distance":"-21097","event_id":"29755"},{"id":"29446566","race_id":"73970","rank":"6465","name":"\u0410\u043d\u0434\u0440\u0435\u0439 \u0414\u043e\u043b\u0436\u0438\u043a\u043e\u0432","bib":"23069","time":"02:19:50","pace":"06:38","hometown":"\u041c\u043e\u0441\u043a\u0432\u0430, Russia","primary_bracket":"M-\u041c\u0443\u0436\u0447\u0438\u043d\u044bMALE","bracket_id":"786309","interval_id":"149013","checkpoint_id":"216049","checkpoint_name":"Finish","checkpoint_distance":"-21097","event_id":"29755"},{"id":"29446024","race_id":"73970","rank":"6466","name":"Veronika Anokhina","bib":"22934","time":"02:19:52","pace":"06:38","hometown":"\u041c\u043e\u0441\u043a\u0432\u0430, Russia","primary_bracket":"F-\u0416\u0435\u043d\u0449\u0438\u043d\u044bFEMALE","bracket_id":"786309","interval_id":"149013","checkpoint_id":"216049","checkpoint_name":"Finish","checkpoint_distance":"-21097","event_id":"29755"},{"id":"29443405","race_id":"73970","rank":"6467","name":"\u042e\u043b\u0438\u044f \u0420\u044f\u0437\u0430\u043d\u0446\u0435\u0432\u0430","bib":"23953","time":"02:19:53","pace":"06:38","hometown":"\u041f\u043e\u0434\u043e\u043b\u044c\u0441\u043a, Russia","primary_bracket":"F-\u0416\u0435\u043d\u0449\u0438\u043d\u044bFEMALE","bracket_id":"786309","interval_id":"149013","checkpoint_id":"216049","checkpoint_name":"Finish","checkpoint_distance":"-21097","event_id":"29755"},{"id":"29441073","race_id":"73970","rank":"6468","name":"Aleksandr Anikin","bib":"26613","time":"02:19:54","pace":"06:38","hometown":"\u041c\u043e\u0441\u043a\u0432\u0430, Russia","primary_bracket":"M-\u041c\u0443\u0436\u0447\u0438\u043d\u044bMALE","bracket_id":"786309","interval_id":"149013","checkpoint_id":"216049","checkpoint_name":"Finish","checkpoint_distance":"-21097","event_id":"29755"},{"id":"29441036","race_id":"73970","rank":"6469","name":"\u0410\u043d\u043d\u0430 \u041a\u0443\u043b\u0451\u0432\u0430","bib":"26606","time":"02:19:55","pace":"06:38","hometown":"\u041c\u043e\u0441\u043a\u0432\u0430, Russia","primary_bracket":"F-\u0416\u0435\u043d\u0449\u0438\u043d\u044bFEMALE","bracket_id":"786309","interval_id":"149013","checkpoint_id":"216049","checkpoint_name":"Finish","checkpoint_distance":"-21097","event_id":"29755"},{"id":"29443498","race_id":"73970","rank":"6470","name":"Elmira Maksutovna","bib":"22418","time":"02:19:57","pace":"06:38","hometown":"\u041c\u043e\u0441\u043a\u0432\u0430, Russia","primary_bracket":"F-\u0416\u0435\u043d\u0449\u0438\u043d\u044bFEMALE","bracket_id":"786309","interval_id":"149013","checkpoint_id":"216049","checkpoint_name":"Finish","checkpoint_distance":"-21097","event_id":"29755"},{"id":"29439884","race_id":"73970","rank":"6471","name":"Nadya Bibikova","bib":"20237","time":"02:19:57","pace":"06:38","hometown":"\u041c\u043e\u0441\u043a\u0432\u0430, Russia","primary_bracket":"F-\u0416\u0435\u043d\u0449\u0438\u043d\u044bFEMALE","bracket_id":"786309","interval_id":"149013","checkpoint_id":"216049","checkpoint_name":"Finish","checkpoint_distance":"-21097","event_id":"29755"},{"id":"29441591","race_id":"73970","rank":"6472","name":"\u0421\u0435\u0440\u0433\u0435\u0439 \u0412\u0430\u043b\u044f\u043b\u044c\u0449\u0438\u043a\u043e\u0432","bib":"23608","time":"02:20:02","pace":"06:39","hometown":"\u041c\u043e\u0441\u043a\u0432\u0430, Russia","primary_bracket":"M-\u041c\u0443\u0436\u0447\u0438\u043d\u044bMALE","bracket_id":"786309","interval_id":"149013","checkpoint_id":"216049","checkpoint_name":"Finish","checkpoint_distance":"-21097","event_id":"29755"},{"id":"29442980","race_id":"73970","rank":"6473","name":"\u0410\u043b\u0435\u043d\u0430 \u0410\u0437\u043e\u0435\u0432\u0430","bib":"22320","time":"02:20:02","pace":"06:39","hometown":"\u041c\u043e\u0441\u043a\u0432\u0430, Russia","primary_bracket":"F-\u0416\u0435\u043d\u0449\u0438\u043d\u044bFEMALE","bracket_id":"786309","interval_id":"149013","checkpoint_id":"216049","checkpoint_name":"Finish","checkpoint_distance":"-21097","event_id":"29755"},{"id":"29444980","race_id":"73970","rank":"6474","name":"\u0414\u0430\u0440\u044c\u044f \u041a\u043e\u0440\u043e\u043b\u0435\u0432\u0430","bib":"27369","time":"02:20:05","pace":"06:39","hometown":"\u041c\u043e\u0441\u043a\u0432\u0430, Russia","primary_bracket":"F-\u0416\u0435\u043d\u0449\u0438\u043d\u044bFEMALE","bracket_id":"786309","interval_id":"149013","checkpoint_id":"216049","checkpoint_name":"Finish","checkpoint_distance":"-21097","event_id":"29755"},{"id":"29445024","race_id":"73970","rank":"6475","name":"\u0421\u0435\u0440\u0433\u0435\u0439 \u041a\u043e\u0447\u0435\u0442\u043a\u043e\u0432","bib":"22707","time":"02:20:08","pace":"06:39","hometown":"\u041c\u043e\u0441\u043a\u0432\u0430, Russia","primary_bracket":"M-\u041c\u0443\u0436\u0447\u0438\u043d\u044bMALE","bracket_id":"786309","interval_id":"149013","checkpoint_id":"216049","checkpoint_name":"Finish","checkpoint_distance":"-21097","event_id":"29755"},{"id":"29442543","race_id":"73970","rank":"6476","name":"\u0418\u0432\u0430\u043d \u041a\u0430\u0437\u0430\u043a\u043e\u0432","bib":"20867","time":"02:20:09","pace":"06:39","hometown":"\u041c\u043e\u0441\u043a\u0432\u0430, Russia","primary_bracket":"M-\u041c\u0443\u0436\u0447\u0438\u043d\u044bMALE","bracket_id":"786309","interval_id":"149013","checkpoint_id":"216049","checkpoint_name":"Finish","checkpoint_distance":"-21097","event_id":"29755"},{"id":"29444552","race_id":"73970","rank":"6477","name":"Viktoria Cherepanova","bib":"24169","time":"02:20:11","pace":"06:39","hometown":"\u041c\u043e\u0441\u043a\u0432\u0430, Russia","primary_bracket":"F-\u0416\u0435\u043d\u0449\u0438\u043d\u044bFEMALE","bracket_id":"786309","interval_id":"149013","checkpoint_id":"216049","checkpoint_name":"Finish","checkpoint_distance":"-21097","event_id":"29755"},{"id":"29438948","race_id":"73970","rank":"6478","name":"\u0412\u0430\u0441\u0438\u043b\u0438\u0439 \u041f\u043e\u0431\u0435\u0440\u0435\u0437\u043e\u0432\u0441\u043a\u0438\u0439","bib":"23106","time":"02:20:14","pace":"06:39","hometown":"\u041c\u043e\u0441\u043a\u0432\u0430, Russia","primary_bracket":"M-\u041c\u0443\u0436\u0447\u0438\u043d\u044bMALE","bracket_id":"786309","interval_id":"149013","checkpoint_id":"216049","checkpoint_name":"Finish","checkpoint_distance":"-21097","event_id":"29755"},{"id":"29446555","race_id":"73970","rank":"6479","name":"\u0415\u043b\u0435\u043d\u0430 \u041f\u0440\u0443\u0441\u0441\u0430\u043a\u043e\u0432\u0430","bib":"27744","time":"02:20:15","pace":"06:39","hometown":"\u041c\u043e\u0441\u043a\u0432\u0430, Russia","primary_bracket":"F-\u0416\u0435\u043d\u0449\u0438\u043d\u044bFEMALE","bracket_id":"786309","interval_id":"149013","checkpoint_id":"216049","checkpoint_name":"Finish","checkpoint_distance":"-21097","event_id":"29755"},{"id":"29440132","race_id":"73970","rank":"6480","name":"\u0410\u043b\u0435\u043a\u0441\u0430\u043d\u0434\u0440 \u0410\u043b\u0435\u043a\u0441\u0430\u043d\u0434\u0440\u043e\u0432","bib":"23330","time":"02:20:15","pace":"06:39","hometown":"\u041c\u043e\u0441\u043a\u0432\u0430, Russia","primary_bracket":"M-\u041c\u0443\u0436\u0447\u0438\u043d\u044bMALE","bracket_id":"786309","interval_id":"149013","checkpoint_id":"216049","checkpoint_name":"Finish","checkpoint_distance":"-21097","event_id":"29755"},{"id":"29444556","race_id":"73970","rank":"6481","name":"\u0421\u0432\u0435\u0442\u043b\u0430\u043d\u0430 \u0410\u0433\u0430\u0435\u0432\u0430","bib":"25721","time":"02:20:15","pace":"06:39","hometown":"\u041c\u043e\u0441\u043a\u0432\u0430, Russia","primary_bracket":"F-\u0416\u0435\u043d\u0449\u0438\u043d\u044bFEMALE","bracket_id":"786309","interval_id":"149013","checkpoint_id":"216049","checkpoint_name":"Finish","checkpoint_distance":"-21097","event_id":"29755"},{"id":"29440928","race_id":"73970","rank":"6482","name":"Hun Jung","bib":"23482","time":"02:20:17","pace":"06:39","hometown":"\u041c\u043e\u0441\u043a\u0432\u0430, Russia","primary_bracket":"M-\u041c\u0443\u0436\u0447\u0438\u043d\u044bMALE","bracket_id":"786309","interval_id":"149013","checkpoint_id":"216049","checkpoint_name":"Finish","checkpoint_distance":"-21097","event_id":"29755"},{"id":"29443083","race_id":"73970","rank":"6483","name":"Ekaterina Chernyaeva","bib":"25440","time":"02:20:18","pace":"06:39","hometown":"\u041c\u043e\u0441\u043a\u0432\u0430, Russia","primary_bracket":"F-\u0416\u0435\u043d\u0449\u0438\u043d\u044bFEMALE","bracket_id":"786309","interval_id":"149013","checkpoint_id":"216049","checkpoint_name":"Finish","checkpoint_distance":"-21097","event_id":"29755"},{"id":"29443545","race_id":"73970","rank":"6484","name":"\u041a\u0440\u0438\u0441\u0442\u0438\u043d\u0430 \u0411\u0430\u043b\u0430\u043a\u0438\u0440\u0435\u0432\u0430","bib":"22427","time":"02:20:19","pace":"06:40","hometown":"\u041c\u043e\u0441\u043a\u0432\u0430, Russia","primary_bracket":"F-\u0416\u0435\u043d\u0449\u0438\u043d\u044bFEMALE","bracket_id":"786309","interval_id":"149013","checkpoint_id":"216049","checkpoint_name":"Finish","checkpoint_distance":"-21097","event_id":"29755"},{"id":"29439776","race_id":"73970","rank":"6485","name":"\u0412\u0430\u043b\u0435\u0440\u0438\u044f \u0411\u0435\u043b\u043e\u0443\u0441\u043e\u0432\u0430","bib":"24814","time":"02:20:20","pace":"06:40","hometown":"\u041c\u043e\u0441\u043a\u0432\u0430, Russia","primary_bracket":"F-\u0416\u0435\u043d\u0449\u0438\u043d\u044bFEMALE","bracket_id":"786309","interval_id":"149013","checkpoint_id":"216049","checkpoint_name":"Finish","checkpoint_distance":"-21097","event_id":"29755"},{"id":"29441520","race_id":"73970","rank":"6486","name":"\u041a\u043e\u043d\u0441\u0442\u0430\u043d\u0442\u0438\u043d \u0422\u0430\u0442\u0430\u0440\u0441\u043a\u0438\u0439","bib":"23594","time":"02:20:21","pace":"06:40","hometown":"\u041c\u043e\u0441\u043a\u0432\u0430, Russia","primary_bracket":"M-\u041c\u0443\u0436\u0447\u0438\u043d\u044bMALE","bracket_id":"786309","interval_id":"149013","checkpoint_id":"216049","checkpoint_name":"Finish","checkpoint_distance":"-21097","event_id":"29755"},{"id":"29443602","race_id":"73970","rank":"6487","name":"\u0410\u043b\u0435\u043a\u0441\u0435\u0439 \u041d\u043e\u0432\u0438\u043a\u043e\u0432","bib":"27103","time":"02:20:24","pace":"06:40","hometown":"\u041f\u0423\u0428\u041a\u0418\u041d\u041e, Russia","primary_bracket":"M-\u041c\u0443\u0436\u0447\u0438\u043d\u044bMALE","bracket_id":"786309","interval_id":"149013","checkpoint_id":"216049","checkpoint_name":"Finish","checkpoint_distance":"-21097","event_id":"29755"},{"id":"29441924","race_id":"73970","rank":"6488","name":"\u0410\u043b\u0435\u043a\u0441\u0435\u0439 \u0418\u043d\u0436\u0435\u0432\u0430\u0442\u043a\u0438\u043d","bib":"23672","time":"02:20:24","pace":"06:40","hometown":"\u0421\u0430\u043d\u043a\u0442-\u041f\u0435\u0442\u0435\u0440\u0431\u0443\u0440\u0433, Russia","primary_bracket":"M-\u041c\u0443\u0436\u0447\u0438\u043d\u044bMALE","bracket_id":"786309","interval_id":"149013","checkpoint_id":"216049","checkpoint_name":"Finish","checkpoint_distance":"-21097","event_id":"29755"},{"id":"29441444","race_id":"73970","rank":"6489","name":"\u0421\u0442\u0430\u043d\u0438\u0441\u043b\u0430\u0432 \u041e\u0434\u0438\u043d\u0446\u043e\u0432","bib":"26686","time":"02:20:26","pace":"06:40","hometown":"\u0414\u041e\u041b\u0413\u041e\u041f\u0420\u0423\u0414\u041d\u042b\u0419, Russia","primary_bracket":"M-\u041c\u0443\u0436\u0447\u0438\u043d\u044bMALE","bracket_id":"786309","interval_id":"149013","checkpoint_id":"216049","checkpoint_name":"Finish","checkpoint_distance":"-21097","event_id":"29755"},{"id":"29446257","race_id":"73970","rank":"6490","name":"\u041b\u0438\u043d\u043e\u0447\u043a\u0430 \u0422\u044e\u0440\u0438\u043d\u0430","bib":"26090","time":"02:20:27","pace":"06:40","hometown":"\u041c\u043e\u0441\u043a\u0432\u0430, Russia","primary_bracket":"F-\u0416\u0435\u043d\u0449\u0438\u043d\u044bFEMALE","bracket_id":"786309","interval_id":"149013","checkpoint_id":"216049","checkpoint_name":"Finish","checkpoint_distance":"-21097","event_id":"29755"},{"id":"29445935","race_id":"73970","rank":"6491","name":"\u041d\u0438\u043a\u043e\u043b\u0430\u0439 \u0411\u0443\u0433\u0430\u0439\u0446\u043e\u0432","bib":"27587","time":"02:20:27","pace":"06:40","hometown":"\u041c\u043e\u0441\u043a\u0432\u0430, Russia","primary_bracket":"M-\u041c\u0443\u0436\u0447\u0438\u043d\u044bMALE","bracket_id":"786309","interval_id":"149013","checkpoint_id":"216049","checkpoint_name":"Finish","checkpoint_distance":"-21097","event_id":"29755"},{"id":"29443438","race_id":"73970","rank":"6492","name":"Valeriy Zastavnyuk","bib":"25508","time":"02:20:28","pace":"06:40","hometown":"\u041c\u043e\u0441\u043a\u0432\u0430, Russia","primary_bracket":"M-\u041c\u0443\u0436\u0447\u0438\u043d\u044bMALE","bracket_id":"786309","interval_id":"149013","checkpoint_id":"216049","checkpoint_name":"Finish","checkpoint_distance":"-21097","event_id":"29755"},{"id":"29591485","race_id":"73970","rank":"6493","name":"\u0422\u0430\u0442\u044c\u044f\u043d\u0430 \u041a\u043e\u0436\u0435\u0432\u043d\u0438\u043a\u043e\u0432\u0430","bib":"28279","time":"02:20:30","pace":"06:40","hometown":"\u041c\u043e\u0441\u043a\u0432\u0430, Russia","primary_bracket":"F-\u0416\u0435\u043d\u0449\u0438\u043d\u044bFEMALE","bracket_id":"786309","interval_id":"149013","checkpoint_id":"216049","checkpoint_name":"Finish","checkpoint_distance":"-21097","event_id":"29755"},{"id":"29439142","race_id":"73970","rank":"6494","name":"\u0412\u043b\u0430\u0434\u0438\u043c\u0438\u0440 \u0411\u0443\u0431\u043b\u0438\u043a\u043e\u0432","bib":"21595","time":"02:20:30","pace":"06:40","hometown":"\u041c\u043e\u0441\u043a\u0432\u0430, Russia","primary_bracket":"M-\u041c\u0443\u0436\u0447\u0438\u043d\u044bMALE","bracket_id":"786309","interval_id":"149013","checkpoint_id":"216049","checkpoint_name":"Finish","checkpoint_distance":"-21097","event_id":"29755"},{"id":"29591461","race_id":"73970","rank":"6495","name":"\u041c\u0430\u043a\u0441\u0438\u043c \u0421\u0442\u0435\u043f\u0430\u043d\u043e\u0432","bib":"28287","time":"02:20:31","pace":"06:40","hometown":"\u041c\u043e\u0441\u043a\u0432\u0430, Russia","primary_bracket":"M-\u041c\u0443\u0436\u0447\u0438\u043d\u044bMALE","bracket_id":"786309","interval_id":"149013","checkpoint_id":"216049","checkpoint_name":"Finish","checkpoint_distance":"-21097","event_id":"29755"},{"id":"29445302","race_id":"73970","rank":"6496","name":"\u041e\u043b\u044c\u0433\u0430 \u041e\u0440\u043b\u043e\u0432\u0430","bib":"24312","time":"02:20:32","pace":"06:40","hometown":"\u041a\u041e\u041d\u0410\u041a\u041e\u0412\u041e, Russia","primary_bracket":"F-\u0416\u0435\u043d\u0449\u0438\u043d\u044bFEMALE","bracket_id":"786309","interval_id":"149013","checkpoint_id":"216049","checkpoint_name":"Finish","checkpoint_distance":"-21097","event_id":"29755"},{"id":"29446144","race_id":"73970","rank":"6497","name":"\u0410\u043d\u0430\u0441\u0442\u0430\u0441\u0438\u044f \u041a\u043e\u0442\u043e\u0432\u0430","bib":"24517","time":"02:20:32","pace":"06:40","hometown":"\u041c\u043e\u0441\u043a\u0432\u0430, Russia","primary_bracket":"F-\u0416\u0435\u043d\u0449\u0438\u043d\u044bFEMALE","bracket_id":"786309","interval_id":"149013","checkpoint_id":"216049","checkpoint_name":"Finish","checkpoint_distance":"-21097","event_id":"29755"},{"id":"29445395","race_id":"73970","rank":"6498","name":"\u0410\u043d\u0430\u0441\u0442\u0430\u0441\u0438\u044f \u0417\u0430\u0441\u0438\u043c\u043e\u0432\u0430","bib":"25876","time":"02:20:34","pace":"06:40","hometown":"\u041c\u043e\u0441\u043a\u0432\u0430, Russia","primary_bracket":"F-\u0416\u0435\u043d\u0449\u0438\u043d\u044bFEMALE","bracket_id":"786309","interval_id":"149013","checkpoint_id":"216049","checkpoint_name":"Finish","checkpoint_distance":"-21097","event_id":"29755"},{"id":"29443435","race_id":"73970","rank":"6499","name":"\u041c\u0430\u043a\u0441\u0438\u043c \u0414\u0443\u0431\u0440\u043e\u0432\u0441\u043a\u0438\u0439","bib":"22406","time":"02:20:35","pace":"06:40","hometown":"\u041c\u043e\u0441\u043a\u0432\u0430, Russia","primary_bracket":"M-\u041c\u0443\u0436\u0447\u0438\u043d\u044bMALE","bracket_id":"786309","interval_id":"149013","checkpoint_id":"216049","checkpoint_name":"Finish","checkpoint_distance":"-21097","event_id":"29755"},{"id":"29439967","race_id":"73970","rank":"6500","name":"Natasha Medinskaya","bib":"21750","time":"02:20:38","pace":"06:40","hometown":"\u041c\u043e\u0441\u043a\u0432\u0430, Russia","primary_bracket":"F-\u0416\u0435\u043d\u0449\u0438\u043d\u044bFEMALE","bracket_id":"786309","interval_id":"149013","checkpoint_id":"216049","checkpoint_name":"Finish","checkpoint_distance":"-21097","event_id":"29755"}]}